{
"meta":{"test_sets":[],"test_metrics":[],"learn_metrics":[{"best_value":"Min","name":"Logloss"}],"launch_mode":"Train","parameters":"","iteration_count":1000,"learn_sets":["learn"],"name":"experiment"},
"iterations":[
{"learn":[0.6079832623],"iteration":0,"passed_time":0.016977366,"remaining_time":16.96038863},
{"learn":[0.5420473509],"iteration":1,"passed_time":0.03462515258,"remaining_time":17.27795114},
{"learn":[0.4857118816],"iteration":2,"passed_time":0.05124578847,"remaining_time":17.0306837},
{"learn":[0.4402601227],"iteration":3,"passed_time":0.06708799389,"remaining_time":16.70491048},
{"learn":[0.4043108541],"iteration":4,"passed_time":0.08247618919,"remaining_time":16.41276165},
{"learn":[0.371483246],"iteration":5,"passed_time":0.09939796231,"remaining_time":16.46692909},
{"learn":[0.346800303],"iteration":6,"passed_time":0.1140258807,"remaining_time":16.17538565},
{"learn":[0.327579487],"iteration":7,"passed_time":0.1326079362,"remaining_time":16.44338408},
{"learn":[0.3093757453],"iteration":8,"passed_time":0.147645713,"remaining_time":16.25743351},
{"learn":[0.2947820213],"iteration":9,"passed_time":0.1632968348,"remaining_time":16.16638665},
{"learn":[0.2832504644],"iteration":10,"passed_time":0.1794970828,"remaining_time":16.13841954},
{"learn":[0.2729684481],"iteration":11,"passed_time":0.1924563735,"remaining_time":15.84557475},
{"learn":[0.2639499101],"iteration":12,"passed_time":0.206278591,"remaining_time":15.66130533},
{"learn":[0.2558546156],"iteration":13,"passed_time":0.2210887767,"remaining_time":15.5709667},
{"learn":[0.2491655396],"iteration":14,"passed_time":0.2371826879,"remaining_time":15.57499651},
{"learn":[0.2438361459],"iteration":15,"passed_time":0.2529405874,"remaining_time":15.55584612},
{"learn":[0.2390293776],"iteration":16,"passed_time":0.2704573114,"remaining_time":15.6387963},
{"learn":[0.2352795842],"iteration":17,"passed_time":0.2853310447,"remaining_time":15.56639366},
{"learn":[0.2321637657],"iteration":18,"passed_time":0.3002256266,"remaining_time":15.50112314},
{"learn":[0.2287798546],"iteration":19,"passed_time":0.3181453764,"remaining_time":15.58912345},
{"learn":[0.2260981151],"iteration":20,"passed_time":0.3340410107,"remaining_time":15.57267379},
{"learn":[0.2236714939],"iteration":21,"passed_time":0.3498177049,"remaining_time":15.55098706},
{"learn":[0.2212969669],"iteration":22,"passed_time":0.3670675652,"remaining_time":15.59239179},
{"learn":[0.2194660424],"iteration":23,"passed_time":0.3831203202,"remaining_time":15.58022636},
{"learn":[0.2178253978],"iteration":24,"passed_time":0.3982540446,"remaining_time":15.53190774},
{"learn":[0.2162948616],"iteration":25,"passed_time":0.4143681331,"remaining_time":15.52286776},
{"learn":[0.2150149576],"iteration":26,"passed_time":0.4315488254,"remaining_time":15.551741},
{"learn":[0.2138885939],"iteration":27,"passed_time":0.4478833719,"remaining_time":15.54795134},
{"learn":[0.212783445],"iteration":28,"passed_time":0.4637983019,"remaining_time":15.52924659},
{"learn":[0.2117489972],"iteration":29,"passed_time":0.4826067061,"remaining_time":15.6042835},
{"learn":[0.2100977235],"iteration":30,"passed_time":0.4991067389,"remaining_time":15.60111064},
{"learn":[0.208945239],"iteration":31,"passed_time":0.5151569692,"remaining_time":15.58349832},
{"learn":[0.2082019845],"iteration":32,"passed_time":0.5302095435,"remaining_time":15.53674632},
{"learn":[0.2073390949],"iteration":33,"passed_time":0.5435360637,"remaining_time":15.44281875},
{"learn":[0.205765373],"iteration":34,"passed_time":0.5573784185,"remaining_time":15.36771925},
{"learn":[0.2051577706],"iteration":35,"passed_time":0.5708199816,"remaining_time":15.28529062},
{"learn":[0.2044129617],"iteration":36,"passed_time":0.5826716126,"remaining_time":15.16520981},
{"learn":[0.2036625813],"iteration":37,"passed_time":0.5929695786,"remaining_time":15.01149302},
{"learn":[0.2029091856],"iteration":38,"passed_time":0.6048159198,"remaining_time":14.90328459},
{"learn":[0.2023091],"iteration":39,"passed_time":0.6180393894,"remaining_time":14.83294535},
{"learn":[0.2018086524],"iteration":40,"passed_time":0.6296711235,"remaining_time":14.72816116},
{"learn":[0.2009315321],"iteration":41,"passed_time":0.6401424202,"remaining_time":14.60134378},
{"learn":[0.2005800523],"iteration":42,"passed_time":0.6510631487,"remaining_time":14.48994031},
{"learn":[0.2000195919],"iteration":43,"passed_time":0.6625203498,"remaining_time":14.39476033},
{"learn":[0.1996531739],"iteration":44,"passed_time":0.6746421908,"remaining_time":14.31740649},
{"learn":[0.1992594205],"iteration":45,"passed_time":0.6866415151,"remaining_time":14.24034794},
{"learn":[0.1988288874],"iteration":46,"passed_time":0.6979167996,"remaining_time":14.15137681},
{"learn":[0.1982885155],"iteration":47,"passed_time":0.7099668678,"remaining_time":14.08100955},
{"learn":[0.1972177401],"iteration":48,"passed_time":0.7220578217,"remaining_time":14.01381609},
{"learn":[0.1967319502],"iteration":49,"passed_time":0.7337228775,"remaining_time":13.94073467},
{"learn":[0.1960996002],"iteration":50,"passed_time":0.7456349503,"remaining_time":13.87465819},
{"learn":[0.195796433],"iteration":51,"passed_time":0.7570811211,"remaining_time":13.80217121},
{"learn":[0.1955024931],"iteration":52,"passed_time":0.7680536954,"remaining_time":13.72352546},
{"learn":[0.194389954],"iteration":53,"passed_time":0.7798428408,"remaining_time":13.66169125},
{"learn":[0.1939656934],"iteration":54,"passed_time":0.7909050109,"remaining_time":13.5891861},
{"learn":[0.1937045123],"iteration":55,"passed_time":0.8025750559,"remaining_time":13.52912237},
{"learn":[0.1933871578],"iteration":56,"passed_time":0.8153579402,"remaining_time":13.48916733},
{"learn":[0.1930864855],"iteration":57,"passed_time":0.8270998882,"remaining_time":13.43324301},
{"learn":[0.192903523],"iteration":58,"passed_time":0.8401526719,"remaining_time":13.39972312},
{"learn":[0.1917597779],"iteration":59,"passed_time":0.857792043,"remaining_time":13.43874201},
{"learn":[0.1912805252],"iteration":60,"passed_time":0.8704216235,"remaining_time":13.39878532},
{"learn":[0.1911863621],"iteration":61,"passed_time":0.880983578,"remaining_time":13.32842897},
{"learn":[0.1909663526],"iteration":62,"passed_time":0.8918097415,"remaining_time":13.26390044},
{"learn":[0.1907809377],"iteration":63,"passed_time":0.9039058248,"remaining_time":13.21962269},
{"learn":[0.1904914157],"iteration":64,"passed_time":0.9181475286,"remaining_time":13.20719907},
{"learn":[0.1903123045],"iteration":65,"passed_time":0.9294253979,"remaining_time":13.1527776},
{"learn":[0.1900236891],"iteration":66,"passed_time":0.941070667,"remaining_time":13.10476018},
{"learn":[0.1893715628],"iteration":67,"passed_time":0.9525265257,"remaining_time":13.0552165},
{"learn":[0.1891470232],"iteration":68,"passed_time":0.9636751658,"remaining_time":13.00263159},
{"learn":[0.1887329372],"iteration":69,"passed_time":0.9751134119,"remaining_time":12.95507819},
{"learn":[0.1884434165],"iteration":70,"passed_time":0.9872123004,"remaining_time":12.9171863},
{"learn":[0.1881373186],"iteration":71,"passed_time":0.9984210518,"remaining_time":12.868538},
{"learn":[0.1879577777],"iteration":72,"passed_time":1.012774252,"remaining_time":12.86084564},
{"learn":[0.1877597959],"iteration":73,"passed_time":1.024244647,"remaining_time":12.81689924},
{"learn":[0.1870753583],"iteration":74,"passed_time":1.036006873,"remaining_time":12.7774181},
{"learn":[0.1868402174],"iteration":75,"passed_time":1.047513816,"remaining_time":12.73556271},
{"learn":[0.1863570013],"iteration":76,"passed_time":1.060307911,"remaining_time":12.7099247},
{"learn":[0.185974407],"iteration":77,"passed_time":1.072257133,"remaining_time":12.67462919},
{"learn":[0.1855727428],"iteration":78,"passed_time":1.083727879,"remaining_time":12.63434654},
{"learn":[0.1852060987],"iteration":79,"passed_time":1.095616448,"remaining_time":12.59958916},
{"learn":[0.184772509],"iteration":80,"passed_time":1.109883719,"remaining_time":12.59238442},
{"learn":[0.1842766448],"iteration":81,"passed_time":1.121861043,"remaining_time":12.55937119},
{"learn":[0.1841355031],"iteration":82,"passed_time":1.136202692,"remaining_time":12.55298637},
{"learn":[0.1835211365],"iteration":83,"passed_time":1.148422875,"remaining_time":12.52327801},
{"learn":[0.1833293211],"iteration":84,"passed_time":1.1620549,"remaining_time":12.50917922},
{"learn":[0.1832089754],"iteration":85,"passed_time":1.173834728,"remaining_time":12.4754063},
{"learn":[0.1830730318],"iteration":86,"passed_time":1.18491905,"remaining_time":12.43484014},
{"learn":[0.1827493838],"iteration":87,"passed_time":1.197010585,"remaining_time":12.40538242},
{"learn":[0.182663897],"iteration":88,"passed_time":1.210972671,"remaining_time":12.39546183},
{"learn":[0.1824881336],"iteration":89,"passed_time":1.221739134,"remaining_time":12.35314013},
{"learn":[0.1821370268],"iteration":90,"passed_time":1.233151582,"remaining_time":12.3179647},
{"learn":[0.1819014248],"iteration":91,"passed_time":1.245344034,"remaining_time":12.29100416},
{"learn":[0.1816520249],"iteration":92,"passed_time":1.258889359,"remaining_time":12.27755536},
{"learn":[0.1814728355],"iteration":93,"passed_time":1.271358132,"remaining_time":12.25372838},
{"learn":[0.1812916596],"iteration":94,"passed_time":1.283087016,"remaining_time":12.2230921},
{"learn":[0.1811304237],"iteration":95,"passed_time":1.294747523,"remaining_time":12.19220584},
{"learn":[0.1810159651],"iteration":96,"passed_time":1.308602732,"remaining_time":12.18214708},
{"learn":[0.1809119045],"iteration":97,"passed_time":1.3203664,"remaining_time":12.15276013},
{"learn":[0.1806380549],"iteration":98,"passed_time":1.335182677,"remaining_time":12.15151103},
{"learn":[0.1804621427],"iteration":99,"passed_time":1.349913506,"remaining_time":12.14922155},
{"learn":[0.1803420781],"iteration":100,"passed_time":1.360993078,"remaining_time":12.11418591},
{"learn":[0.1802219144],"iteration":101,"passed_time":1.3715912,"remaining_time":12.07538135},
{"learn":[0.180075616],"iteration":102,"passed_time":1.381976647,"remaining_time":12.03527236},
{"learn":[0.1799027082],"iteration":103,"passed_time":1.393670517,"remaining_time":12.00700753},
{"learn":[0.1797141858],"iteration":104,"passed_time":1.40817668,"remaining_time":12.00302979},
{"learn":[0.1795608606],"iteration":105,"passed_time":1.421259218,"remaining_time":11.98684662},
{"learn":[0.1794535389],"iteration":106,"passed_time":1.43392148,"remaining_time":11.96721384},
{"learn":[0.1793055743],"iteration":107,"passed_time":1.445214457,"remaining_time":11.93640088},
{"learn":[0.1787655644],"iteration":108,"passed_time":1.45788346,"remaining_time":11.91719416},
{"learn":[0.1783403817],"iteration":109,"passed_time":1.469380114,"remaining_time":11.88862093},
{"learn":[0.1780659636],"iteration":110,"passed_time":1.481016667,"remaining_time":11.86147583},
{"learn":[0.177926234],"iteration":111,"passed_time":1.492223165,"remaining_time":11.83119795},
{"learn":[0.177831677],"iteration":112,"passed_time":1.505625786,"remaining_time":11.81849621},
{"learn":[0.1777105133],"iteration":113,"passed_time":1.517852721,"remaining_time":11.79664483},
{"learn":[0.1776575108],"iteration":114,"passed_time":1.529115733,"remaining_time":11.76754281},
{"learn":[0.1774236935],"iteration":115,"passed_time":1.54038672,"remaining_time":11.73880914},
{"learn":[0.1771273427],"iteration":116,"passed_time":1.551943465,"remaining_time":11.71253059},
{"learn":[0.1770409362],"iteration":117,"passed_time":1.562461849,"remaining_time":11.67874026},
{"learn":[0.176912911],"iteration":118,"passed_time":1.573266693,"remaining_time":11.64746182},
{"learn":[0.1766384666],"iteration":119,"passed_time":1.585014632,"remaining_time":11.62344063},
{"learn":[0.1764264157],"iteration":120,"passed_time":1.597170536,"remaining_time":11.60258596},
{"learn":[0.176262187],"iteration":121,"passed_time":1.610021837,"remaining_time":11.58687846},
{"learn":[0.1761706157],"iteration":122,"passed_time":1.62112901,"remaining_time":11.55878164},
{"learn":[0.1761184013],"iteration":123,"passed_time":1.631846182,"remaining_time":11.52820367},
{"learn":[0.1759404843],"iteration":124,"passed_time":1.643996165,"remaining_time":11.50797316},
{"learn":[0.1756805296],"iteration":125,"passed_time":1.655753171,"remaining_time":11.48514501},
{"learn":[0.1756245913],"iteration":126,"passed_time":1.666095229,"remaining_time":11.45276484},
{"learn":[0.1754731875],"iteration":127,"passed_time":1.677544625,"remaining_time":11.42827276},
{"learn":[0.175414007],"iteration":128,"passed_time":1.688665835,"remaining_time":11.40176699},
{"learn":[0.1751719203],"iteration":129,"passed_time":1.70218975,"remaining_time":11.39157756},
{"learn":[0.1750122672],"iteration":130,"passed_time":1.71425123,"remaining_time":11.37163602},
{"learn":[0.1749324005],"iteration":131,"passed_time":1.72591904,"remaining_time":11.3492252},
{"learn":[0.174767598],"iteration":132,"passed_time":1.737888489,"remaining_time":11.32894226},
{"learn":[0.1747130994],"iteration":133,"passed_time":1.749164966,"remaining_time":11.30430493},
{"learn":[0.1744520937],"iteration":134,"passed_time":1.765327204,"remaining_time":11.3111706},
{"learn":[0.1743124139],"iteration":135,"passed_time":1.776968666,"remaining_time":11.28897741},
{"learn":[0.1741052013],"iteration":136,"passed_time":1.78813023,"remaining_time":11.26391524},
{"learn":[0.1739951954],"iteration":137,"passed_time":1.800831714,"remaining_time":11.24867346},
{"learn":[0.1737516255],"iteration":138,"passed_time":1.814788179,"remaining_time":11.24124189},
{"learn":[0.1736783563],"iteration":139,"passed_time":1.828565654,"remaining_time":11.23261759},
{"learn":[0.1735918312],"iteration":140,"passed_time":1.842843956,"remaining_time":11.22697133},
{"learn":[0.1735120021],"iteration":141,"passed_time":1.854120462,"remaining_time":11.20306589},
{"learn":[0.1733449685],"iteration":142,"passed_time":1.865991028,"remaining_time":11.18289728},
{"learn":[0.1732867868],"iteration":143,"passed_time":1.87656745,"remaining_time":11.15515095},
{"learn":[0.1732498366],"iteration":144,"passed_time":1.886864514,"remaining_time":11.1259942},
{"learn":[0.1731234694],"iteration":145,"passed_time":1.900918841,"remaining_time":11.11907322},
{"learn":[0.1729839114],"iteration":146,"passed_time":1.91176403,"remaining_time":11.09343345},
{"learn":[0.1727455136],"iteration":147,"passed_time":1.924262357,"remaining_time":11.07751033},
{"learn":[0.172472784],"iteration":148,"passed_time":1.94013522,"remaining_time":11.08090652},
{"learn":[0.1723752013],"iteration":149,"passed_time":1.956257373,"remaining_time":11.08545845},
{"learn":[0.1722431284],"iteration":150,"passed_time":1.973988053,"remaining_time":11.09878051},
{"learn":[0.1720926509],"iteration":151,"passed_time":1.98769096,"remaining_time":11.08922325},
{"learn":[0.1718372671],"iteration":152,"passed_time":2.003998396,"remaining_time":11.09403034},
{"learn":[0.1717925398],"iteration":153,"passed_time":2.016557246,"remaining_time":11.07797032},
{"learn":[0.1717183993],"iteration":154,"passed_time":2.027526684,"remaining_time":11.05329063},
{"learn":[0.1716528885],"iteration":155,"passed_time":2.038526229,"remaining_time":11.0289496},
{"learn":[0.1715870833],"iteration":156,"passed_time":2.049447197,"remaining_time":11.00435661},
{"learn":[0.1714541239],"iteration":157,"passed_time":2.060964159,"remaining_time":10.9831128},
{"learn":[0.1713895689],"iteration":158,"passed_time":2.07188064,"remaining_time":10.95881521},
{"learn":[0.1713013046],"iteration":159,"passed_time":2.08311574,"remaining_time":10.93635763},
{"learn":[0.1712512304],"iteration":160,"passed_time":2.09711775,"remaining_time":10.92845834},
{"learn":[0.1710667024],"iteration":161,"passed_time":2.109832288,"remaining_time":10.91382381},
{"learn":[0.1709939083],"iteration":162,"passed_time":2.12430541,"remaining_time":10.90824312},
{"learn":[0.1709471524],"iteration":163,"passed_time":2.135685228,"remaining_time":10.88678567},
{"learn":[0.1708671909],"iteration":164,"passed_time":2.147362957,"remaining_time":10.86695799},
{"learn":[0.1707976567],"iteration":165,"passed_time":2.158222572,"remaining_time":10.84311822},
{"learn":[0.1707297747],"iteration":166,"passed_time":2.168993323,"remaining_time":10.81899065},
{"learn":[0.1706067059],"iteration":167,"passed_time":2.180590143,"remaining_time":10.79911309},
{"learn":[0.1705362068],"iteration":168,"passed_time":2.194803233,"remaining_time":10.79219815},
{"learn":[0.170465175],"iteration":169,"passed_time":2.206309235,"remaining_time":10.77198038},
{"learn":[0.1703740614],"iteration":170,"passed_time":2.216996942,"remaining_time":10.74789746},
{"learn":[0.1702603513],"iteration":171,"passed_time":2.228702353,"remaining_time":10.72886946},
{"learn":[0.1701736701],"iteration":172,"passed_time":2.239555606,"remaining_time":10.70585252},
{"learn":[0.1701005545],"iteration":173,"passed_time":2.250342066,"remaining_time":10.68265831},
{"learn":[0.1700331179],"iteration":174,"passed_time":2.260939306,"remaining_time":10.65871387},
{"learn":[0.1699075552],"iteration":175,"passed_time":2.272406666,"remaining_time":10.63899484},
{"learn":[0.1697885235],"iteration":176,"passed_time":2.283620076,"remaining_time":10.61818826},
{"learn":[0.1695133351],"iteration":177,"passed_time":2.297384536,"remaining_time":10.60927016},
{"learn":[0.1692810498],"iteration":178,"passed_time":2.30948636,"remaining_time":10.59267208},
{"learn":[0.1692166792],"iteration":179,"passed_time":2.322640301,"remaining_time":10.58091693},
{"learn":[0.1691673917],"iteration":180,"passed_time":2.338456268,"remaining_time":10.58119162},
{"learn":[0.1691232242],"iteration":181,"passed_time":2.351617663,"remaining_time":10.56935851},
{"learn":[0.1689822472],"iteration":182,"passed_time":2.367548753,"remaining_time":10.56987613},
{"learn":[0.1689019327],"iteration":183,"passed_time":2.37864159,"remaining_time":10.54875835},
{"learn":[0.1688446031],"iteration":184,"passed_time":2.392652717,"remaining_time":10.54060521},
{"learn":[0.16877092],"iteration":185,"passed_time":2.403870846,"remaining_time":10.52016596},
{"learn":[0.1686849753],"iteration":186,"passed_time":2.415028893,"remaining_time":10.49956412},
{"learn":[0.1685609703],"iteration":187,"passed_time":2.426235661,"remaining_time":10.47927317},
{"learn":[0.1685044825],"iteration":188,"passed_time":2.43721605,"remaining_time":10.45810696},
{"learn":[0.1683468495],"iteration":189,"passed_time":2.449314567,"remaining_time":10.44181473},
{"learn":[0.168296745],"iteration":190,"passed_time":2.460927256,"remaining_time":10.42350864},
{"learn":[0.1682216544],"iteration":191,"passed_time":2.474569892,"remaining_time":10.41381496},
{"learn":[0.1681359292],"iteration":192,"passed_time":2.487301351,"remaining_time":10.40027041},
{"learn":[0.1679023269],"iteration":193,"passed_time":2.501304773,"remaining_time":10.3920188},
{"learn":[0.1678440795],"iteration":194,"passed_time":2.514519707,"remaining_time":10.38045315},
{"learn":[0.1676870258],"iteration":195,"passed_time":2.526920585,"remaining_time":10.36553138},
{"learn":[0.1676521368],"iteration":196,"passed_time":2.537415896,"remaining_time":10.34286784},
{"learn":[0.1675831982],"iteration":197,"passed_time":2.548132587,"remaining_time":10.32122391},
{"learn":[0.1673555514],"iteration":198,"passed_time":2.559591781,"remaining_time":10.30267848},
{"learn":[0.1671066161],"iteration":199,"passed_time":2.570082444,"remaining_time":10.28032978},
{"learn":[0.1670512573],"iteration":200,"passed_time":2.580795218,"remaining_time":10.25898198},
{"learn":[0.1668213785],"iteration":201,"passed_time":2.595516369,"remaining_time":10.25357456},
{"learn":[0.1666244109],"iteration":202,"passed_time":2.607504011,"remaining_time":10.23734333},
{"learn":[0.1665855622],"iteration":203,"passed_time":2.618281745,"remaining_time":10.21643269},
{"learn":[0.1665082114],"iteration":204,"passed_time":2.629561077,"remaining_time":10.19756613},
{"learn":[0.1664365535],"iteration":205,"passed_time":2.640898196,"remaining_time":10.17899596},
{"learn":[0.1664009842],"iteration":206,"passed_time":2.651209597,"remaining_time":10.15656623},
{"learn":[0.1663464128],"iteration":207,"passed_time":2.662231703,"remaining_time":10.13695918},
{"learn":[0.1662007137],"iteration":208,"passed_time":2.674695607,"remaining_time":10.12289103},
{"learn":[0.1661321901],"iteration":209,"passed_time":2.68856406,"remaining_time":10.11412194},
{"learn":[0.1659729709],"iteration":210,"passed_time":2.701290259,"remaining_time":10.10103324},
{"learn":[0.1658018967],"iteration":211,"passed_time":2.713373409,"remaining_time":10.08555776},
{"learn":[0.1655863866],"iteration":212,"passed_time":2.723979876,"remaining_time":10.06465804},
{"learn":[0.1654775924],"iteration":213,"passed_time":2.735565424,"remaining_time":10.04745058},
{"learn":[0.1653252187],"iteration":214,"passed_time":2.747401947,"remaining_time":10.03121176},
{"learn":[0.1652033419],"iteration":215,"passed_time":2.759161708,"remaining_time":10.01473509},
{"learn":[0.1650498308],"iteration":216,"passed_time":2.772125137,"remaining_time":10.00264508},
{"learn":[0.164986426],"iteration":217,"passed_time":2.786754097,"remaining_time":9.996521577},
{"learn":[0.1648752873],"iteration":218,"passed_time":2.799850792,"remaining_time":9.984856021},
{"learn":[0.1648058548],"iteration":219,"passed_time":2.812751745,"remaining_time":9.972483459},
{"learn":[0.164650962],"iteration":220,"passed_time":2.829165808,"remaining_time":9.972489433},
{"learn":[0.1646135655],"iteration":221,"passed_time":2.840622448,"remaining_time":9.954974166},
{"learn":[0.1645773224],"iteration":222,"passed_time":2.85331717,"remaining_time":9.941827089},
{"learn":[0.1644243593],"iteration":223,"passed_time":2.865864939,"remaining_time":9.928174966},
{"learn":[0.1643073857],"iteration":224,"passed_time":2.878037203,"remaining_time":9.913239255},
{"learn":[0.1642093564],"iteration":225,"passed_time":2.89262655,"remaining_time":9.906605973},
{"learn":[0.1641560693],"iteration":226,"passed_time":2.906705573,"remaining_time":9.898164792},
{"learn":[0.1639008659],"iteration":227,"passed_time":2.918422615,"remaining_time":9.881676573},
{"learn":[0.1638612124],"iteration":228,"passed_time":2.930299142,"remaining_time":9.86576698},
{"learn":[0.163795683],"iteration":229,"passed_time":2.9438298,"remaining_time":9.8554302},
{"learn":[0.1637169974],"iteration":230,"passed_time":2.958406554,"remaining_time":9.848548224},
{"learn":[0.16367207],"iteration":231,"passed_time":2.969595679,"remaining_time":9.830385695},
{"learn":[0.1635687442],"iteration":232,"passed_time":2.985216665,"remaining_time":9.826872025},
{"learn":[0.1635075761],"iteration":233,"passed_time":2.998977829,"remaining_time":9.81716674},
{"learn":[0.1634528692],"iteration":234,"passed_time":3.014029191,"remaining_time":9.811626942},
{"learn":[0.1633971512],"iteration":235,"passed_time":3.026372402,"remaining_time":9.797239471},
{"learn":[0.1633244818],"iteration":236,"passed_time":3.038117636,"remaining_time":9.78094412},
{"learn":[0.1629861525],"iteration":237,"passed_time":3.050274131,"remaining_time":9.766003731},
{"learn":[0.1629157659],"iteration":238,"passed_time":3.06119489,"remaining_time":9.747151929},
{"learn":[0.1628724878],"iteration":239,"passed_time":3.073105049,"remaining_time":9.731499322},
{"learn":[0.1627154143],"iteration":240,"passed_time":3.086831139,"remaining_time":9.721596823},
{"learn":[0.162553113],"iteration":241,"passed_time":3.099332712,"remaining_time":9.707827256},
{"learn":[0.1625055374],"iteration":242,"passed_time":3.110676494,"remaining_time":9.69046134},
{"learn":[0.1624061894],"iteration":243,"passed_time":3.122731902,"remaining_time":9.675349663},
{"learn":[0.162365863],"iteration":244,"passed_time":3.134291873,"remaining_time":9.65873618},
{"learn":[0.1623345352],"iteration":245,"passed_time":3.144441424,"remaining_time":9.637840789},
{"learn":[0.1622703309],"iteration":246,"passed_time":3.156389814,"remaining_time":9.622516317},
{"learn":[0.1622216976],"iteration":247,"passed_time":3.167768871,"remaining_time":9.605492706},
{"learn":[0.1621893333],"iteration":248,"passed_time":3.179839267,"remaining_time":9.590599556},
{"learn":[0.1620898446],"iteration":249,"passed_time":3.193321195,"remaining_time":9.579963584},
{"learn":[0.1620297889],"iteration":250,"passed_time":3.205035772,"remaining_time":9.564031049},
{"learn":[0.1618758569],"iteration":251,"passed_time":3.216820209,"remaining_time":9.54833935},
{"learn":[0.1618189274],"iteration":252,"passed_time":3.228216237,"remaining_time":9.531531734},
{"learn":[0.1617772189],"iteration":253,"passed_time":3.238908983,"remaining_time":9.512701187},
{"learn":[0.1616246359],"iteration":254,"passed_time":3.251344104,"remaining_time":9.499024931},
{"learn":[0.1615823212],"iteration":255,"passed_time":3.263197338,"remaining_time":9.483667263},
{"learn":[0.1614214266],"iteration":256,"passed_time":3.274580823,"remaining_time":9.466978798},
{"learn":[0.1613708706],"iteration":257,"passed_time":3.288485683,"remaining_time":9.457582856},
{"learn":[0.1612219752],"iteration":258,"passed_time":3.299876151,"remaining_time":9.440958408},
{"learn":[0.1611153018],"iteration":259,"passed_time":3.317623061,"remaining_time":9.442465634},
{"learn":[0.1610415922],"iteration":260,"passed_time":3.329049765,"remaining_time":9.425930179},
{"learn":[0.1610117964],"iteration":261,"passed_time":3.340877823,"remaining_time":9.410564249},
{"learn":[0.1609481864],"iteration":262,"passed_time":3.352068511,"remaining_time":9.393439135},
{"learn":[0.1608574363],"iteration":263,"passed_time":3.363253819,"remaining_time":9.37634398},
{"learn":[0.1607313183],"iteration":264,"passed_time":3.375414341,"remaining_time":9.361998268},
{"learn":[0.1606607531],"iteration":265,"passed_time":3.388644614,"remaining_time":9.350620851},
{"learn":[0.1606282861],"iteration":266,"passed_time":3.399280956,"remaining_time":9.332108391},
{"learn":[0.1605851804],"iteration":267,"passed_time":3.410661064,"remaining_time":9.31568619},
{"learn":[0.1603962965],"iteration":268,"passed_time":3.421480205,"remaining_time":9.297777062},
{"learn":[0.1603275555],"iteration":269,"passed_time":3.432382118,"remaining_time":9.280144245},
{"learn":[0.160235616],"iteration":270,"passed_time":3.443452463,"remaining_time":9.263014191},
{"learn":[0.1601169826],"iteration":271,"passed_time":3.455326075,"remaining_time":9.248078613},
{"learn":[0.1600756885],"iteration":272,"passed_time":3.46623958,"remaining_time":9.230608699},
{"learn":[0.1600110897],"iteration":273,"passed_time":3.481545583,"remaining_time":9.224825159},
{"learn":[0.1599476891],"iteration":274,"passed_time":3.492703491,"remaining_time":9.208036475},
{"learn":[0.1599043012],"iteration":275,"passed_time":3.5052729,"remaining_time":9.19499123},
{"learn":[0.1598238475],"iteration":276,"passed_time":3.517611823,"remaining_time":9.181347826},
{"learn":[0.1597795912],"iteration":277,"passed_time":3.528511672,"remaining_time":9.163976358},
{"learn":[0.1597329878],"iteration":278,"passed_time":3.541184062,"remaining_time":9.151231931},
{"learn":[0.1596828939],"iteration":279,"passed_time":3.556309581,"remaining_time":9.144796067},
{"learn":[0.1594880835],"iteration":280,"passed_time":3.568801517,"remaining_time":9.131559754},
{"learn":[0.1594382636],"iteration":281,"passed_time":3.581516436,"remaining_time":9.118896457},
{"learn":[0.1593762869],"iteration":282,"passed_time":3.593702987,"remaining_time":9.104894139},
{"learn":[0.1593250736],"iteration":283,"passed_time":3.605384693,"remaining_time":9.089631832},
{"learn":[0.159303052],"iteration":284,"passed_time":3.615749733,"remaining_time":9.071091436},
{"learn":[0.1592758681],"iteration":285,"passed_time":3.626572581,"remaining_time":9.053751128},
{"learn":[0.1592412871],"iteration":286,"passed_time":3.637409163,"remaining_time":9.03649036},
{"learn":[0.1591172673],"iteration":287,"passed_time":3.648773553,"remaining_time":9.020579061},
{"learn":[0.1589739985],"iteration":288,"passed_time":3.660351267,"remaining_time":9.005224051},
{"learn":[0.1589710512],"iteration":289,"passed_time":3.67001544,"remaining_time":8.985210215},
{"learn":[0.1589179678],"iteration":290,"passed_time":3.68250404,"remaining_time":8.972149018},
{"learn":[0.1588182289],"iteration":291,"passed_time":3.694343839,"remaining_time":8.957518623},
{"learn":[0.1587037643],"iteration":292,"passed_time":3.706296787,"remaining_time":8.943180302},
{"learn":[0.1586319794],"iteration":293,"passed_time":3.718022836,"remaining_time":8.928313341},
{"learn":[0.1585472997],"iteration":294,"passed_time":3.729484595,"remaining_time":8.912836067},
{"learn":[0.1585131882],"iteration":295,"passed_time":3.739456879,"remaining_time":8.893843388},
{"learn":[0.1584697],"iteration":296,"passed_time":3.750910874,"remaining_time":8.878418668},
{"learn":[0.1584015106],"iteration":297,"passed_time":3.763705199,"remaining_time":8.86617802},
{"learn":[0.158339434],"iteration":298,"passed_time":3.780024718,"remaining_time":8.862198419},
{"learn":[0.1583179649],"iteration":299,"passed_time":3.790508217,"remaining_time":8.844519174},
{"learn":[0.1582490271],"iteration":300,"passed_time":3.8031011,"remaining_time":8.831786276},
{"learn":[0.1580815543],"iteration":301,"passed_time":3.819382128,"remaining_time":8.82757856},
{"learn":[0.1580393912],"iteration":302,"passed_time":3.831586171,"remaining_time":8.813912743},
{"learn":[0.1579388365],"iteration":303,"passed_time":3.842449874,"remaining_time":8.797187869},
{"learn":[0.1578811395],"iteration":304,"passed_time":3.853684984,"remaining_time":8.78134775},
{"learn":[0.1578262264],"iteration":305,"passed_time":3.864887223,"remaining_time":8.765463179},
{"learn":[0.1577559351],"iteration":306,"passed_time":3.878504441,"remaining_time":8.755060514},
{"learn":[0.1577242617],"iteration":307,"passed_time":3.88953315,"remaining_time":8.738821232},
{"learn":[0.1576467246],"iteration":308,"passed_time":3.901450162,"remaining_time":8.724602141},
{"learn":[0.1574982511],"iteration":309,"passed_time":3.912535184,"remaining_time":8.708546055},
{"learn":[0.1574854985],"iteration":310,"passed_time":3.922769813,"remaining_time":8.690637945},
{"learn":[0.1574438429],"iteration":311,"passed_time":3.93413842,"remaining_time":8.675279593},
{"learn":[0.1573758342],"iteration":312,"passed_time":3.944826768,"remaining_time":8.658453642},
{"learn":[0.1572503173],"iteration":313,"passed_time":3.95608418,"remaining_time":8.642910023},
{"learn":[0.1571383952],"iteration":314,"passed_time":3.969813726,"remaining_time":8.632769531},
{"learn":[0.1570798261],"iteration":315,"passed_time":3.982755775,"remaining_time":8.62090174},
{"learn":[0.1570417043],"iteration":316,"passed_time":3.993135021,"remaining_time":8.603505424},
{"learn":[0.1569563325],"iteration":317,"passed_time":4.005148512,"remaining_time":8.589658129},
{"learn":[0.1569016481],"iteration":318,"passed_time":4.017050906,"remaining_time":8.575585164},
{"learn":[0.1567998062],"iteration":319,"passed_time":4.028849359,"remaining_time":8.561304888},
{"learn":[0.1566616098],"iteration":320,"passed_time":4.040000644,"remaining_time":8.545671144},
{"learn":[0.1565320025],"iteration":321,"passed_time":4.050926101,"remaining_time":8.529589741},
{"learn":[0.1565051552],"iteration":322,"passed_time":4.062217195,"remaining_time":8.514306629},
{"learn":[0.1564200483],"iteration":323,"passed_time":4.075426779,"remaining_time":8.503050934},
{"learn":[0.1563614888],"iteration":324,"passed_time":4.087208901,"remaining_time":8.488818487},
{"learn":[0.1561944946],"iteration":325,"passed_time":4.099432982,"remaining_time":8.475514815},
{"learn":[0.1561403977],"iteration":326,"passed_time":4.110708076,"remaining_time":8.460264633},
{"learn":[0.1560682418],"iteration":327,"passed_time":4.122519132,"remaining_time":8.446136757},
{"learn":[0.1560343225],"iteration":328,"passed_time":4.134274464,"remaining_time":8.431909318},
{"learn":[0.1559768785],"iteration":329,"passed_time":4.150315618,"remaining_time":8.426398376},
{"learn":[0.1558581457],"iteration":330,"passed_time":4.160813233,"remaining_time":8.409619496},
{"learn":[0.1558260907],"iteration":331,"passed_time":4.172747037,"remaining_time":8.395768134},
{"learn":[0.1557897593],"iteration":332,"passed_time":4.185246717,"remaining_time":8.383061742},
{"learn":[0.1557423965],"iteration":333,"passed_time":4.19743988,"remaining_time":8.369745389},
{"learn":[0.1557302945],"iteration":334,"passed_time":4.207425808,"remaining_time":8.352054217},
{"learn":[0.1557149686],"iteration":335,"passed_time":4.217850038,"remaining_time":8.335275075},
{"learn":[0.1556603145],"iteration":336,"passed_time":4.229042299,"remaining_time":8.320044641},
{"learn":[0.1556555046],"iteration":337,"passed_time":4.238919637,"remaining_time":8.30226272},
{"learn":[0.1556104384],"iteration":338,"passed_time":4.250414417,"remaining_time":8.287681209},
{"learn":[0.1555928075],"iteration":339,"passed_time":4.26131592,"remaining_time":8.271966198},
{"learn":[0.1555572807],"iteration":340,"passed_time":4.274868088,"remaining_time":8.261401964},
{"learn":[0.1555345988],"iteration":341,"passed_time":4.285672872,"remaining_time":8.245534355},
{"learn":[0.1555077179],"iteration":342,"passed_time":4.297227112,"remaining_time":8.231131816},
{"learn":[0.1555036016],"iteration":343,"passed_time":4.311354985,"remaining_time":8.221653693},
{"learn":[0.1554064243],"iteration":344,"passed_time":4.322953909,"remaining_time":8.207347276},
{"learn":[0.1553452021],"iteration":345,"passed_time":4.334322356,"remaining_time":8.192620869},
{"learn":[0.1552856799],"iteration":346,"passed_time":4.345395456,"remaining_time":8.17735802},
{"learn":[0.1552372401],"iteration":347,"passed_time":4.356293993,"remaining_time":8.161792195},
{"learn":[0.1551962474],"iteration":348,"passed_time":4.36941336,"remaining_time":8.150395695},
{"learn":[0.1551948803],"iteration":349,"passed_time":4.378867655,"remaining_time":8.132182788},
{"learn":[0.1551149981],"iteration":350,"passed_time":4.390902355,"remaining_time":8.118790964},
{"learn":[0.1550590875],"iteration":351,"passed_time":4.402255293,"remaining_time":8.10415179},
{"learn":[0.1550167857],"iteration":352,"passed_time":4.412748951,"remaining_time":8.087956293},
{"learn":[0.1549556156],"iteration":353,"passed_time":4.424174243,"remaining_time":8.073493111},
{"learn":[0.1548999541],"iteration":354,"passed_time":4.435350435,"remaining_time":8.058594451},
{"learn":[0.1548577405],"iteration":355,"passed_time":4.447740251,"remaining_time":8.04591214},
{"learn":[0.1547698117],"iteration":356,"passed_time":4.459360344,"remaining_time":8.031845101},
{"learn":[0.1547284978],"iteration":357,"passed_time":4.472556703,"remaining_time":8.020618446},
{"learn":[0.1546285306],"iteration":358,"passed_time":4.483211029,"remaining_time":8.004841976},
{"learn":[0.1545919347],"iteration":359,"passed_time":4.493977442,"remaining_time":7.98929323},
{"learn":[0.1545263831],"iteration":360,"passed_time":4.506396433,"remaining_time":7.976696178},
{"learn":[0.154440721],"iteration":361,"passed_time":4.519604684,"remaining_time":7.965491128},
{"learn":[0.1543963982],"iteration":362,"passed_time":4.530797255,"remaining_time":7.950737883},
{"learn":[0.1543382991],"iteration":363,"passed_time":4.542425673,"remaining_time":7.936765737},
{"learn":[0.1542910095],"iteration":364,"passed_time":4.554694216,"remaining_time":7.923920074},
{"learn":[0.1542349466],"iteration":365,"passed_time":4.567571355,"remaining_time":7.9121318},
{"learn":[0.1541921618],"iteration":366,"passed_time":4.580545182,"remaining_time":7.90050436},
{"learn":[0.1541308734],"iteration":367,"passed_time":4.591856052,"remaining_time":7.886013655},
{"learn":[0.1541007235],"iteration":368,"passed_time":4.602423688,"remaining_time":7.870269233},
{"learn":[0.1540575259],"iteration":369,"passed_time":4.613480989,"remaining_time":7.855386548},
{"learn":[0.1540055659],"iteration":370,"passed_time":4.625245068,"remaining_time":7.84172277},
{"learn":[0.1539477853],"iteration":371,"passed_time":4.63636772,"remaining_time":7.826986366},
{"learn":[0.1538885087],"iteration":372,"passed_time":4.647722642,"remaining_time":7.812659776},
{"learn":[0.1538511512],"iteration":373,"passed_time":4.65850831,"remaining_time":7.797396262},
{"learn":[0.1538229025],"iteration":374,"passed_time":4.672138773,"remaining_time":7.786897955},
{"learn":[0.1537550517],"iteration":375,"passed_time":4.684420419,"remaining_time":7.774144526},
{"learn":[0.1537079094],"iteration":376,"passed_time":4.696585951,"remaining_time":7.761201718},
{"learn":[0.1536642474],"iteration":377,"passed_time":4.707390274,"remaining_time":7.74602315},
{"learn":[0.1536121114],"iteration":378,"passed_time":4.718881879,"remaining_time":7.731993791},
{"learn":[0.153582042],"iteration":379,"passed_time":4.729709165,"remaining_time":7.7168939},
{"learn":[0.1535577652],"iteration":380,"passed_time":4.743175774,"remaining_time":7.706104473},
{"learn":[0.1535132289],"iteration":381,"passed_time":4.755919696,"remaining_time":7.694131865},
{"learn":[0.1535033769],"iteration":382,"passed_time":4.767949918,"remaining_time":7.681005481},
{"learn":[0.1534126993],"iteration":383,"passed_time":4.780546427,"remaining_time":7.668793227},
{"learn":[0.1533226146],"iteration":384,"passed_time":4.794050887,"remaining_time":7.658029338},
{"learn":[0.1532761792],"iteration":385,"passed_time":4.80936224,"remaining_time":7.650125428},
{"learn":[0.153224816],"iteration":386,"passed_time":4.820518684,"remaining_time":7.635601947},
{"learn":[0.1531855299],"iteration":387,"passed_time":4.832227902,"remaining_time":7.621967721},
{"learn":[0.1531434789],"iteration":388,"passed_time":4.844173717,"remaining_time":7.608715016},
{"learn":[0.1531335575],"iteration":389,"passed_time":4.855070381,"remaining_time":7.593828032},
{"learn":[0.1530874035],"iteration":390,"passed_time":4.868256111,"remaining_time":7.582526781},
{"learn":[0.1530215745],"iteration":391,"passed_time":4.879564957,"remaining_time":7.568304832},
{"learn":[0.1529660586],"iteration":392,"passed_time":4.891192484,"remaining_time":7.554589918},
{"learn":[0.152883435],"iteration":393,"passed_time":4.902471295,"remaining_time":7.54034925},
{"learn":[0.1528465722],"iteration":394,"passed_time":4.914168249,"remaining_time":7.526764028},
{"learn":[0.1528346135],"iteration":395,"passed_time":4.925151774,"remaining_time":7.512100181},
{"learn":[0.1527957439],"iteration":396,"passed_time":4.937450472,"remaining_time":7.499452481},
{"learn":[0.1527568359],"iteration":397,"passed_time":4.949246841,"remaining_time":7.48604673},
{"learn":[0.1527261552],"iteration":398,"passed_time":4.962748305,"remaining_time":7.475217372},
{"learn":[0.1526789923],"iteration":399,"passed_time":4.975114839,"remaining_time":7.462672258},
{"learn":[0.1526463286],"iteration":400,"passed_time":4.986889127,"remaining_time":7.449243359},
{"learn":[0.1526068168],"iteration":401,"passed_time":4.998894532,"remaining_time":7.436166493},
{"learn":[0.152562322],"iteration":402,"passed_time":5.010826322,"remaining_time":7.422985891},
{"learn":[0.1524948968],"iteration":403,"passed_time":5.023743274,"remaining_time":7.41126483},
{"learn":[0.1524677122],"iteration":404,"passed_time":5.035014441,"remaining_time":7.397119981},
{"learn":[0.1524336389],"iteration":405,"passed_time":5.045419295,"remaining_time":7.381721825},
{"learn":[0.1523790356],"iteration":406,"passed_time":5.056846561,"remaining_time":7.367837863},
{"learn":[0.1523340305],"iteration":407,"passed_time":5.070489687,"remaining_time":7.357181114},
{"learn":[0.1522995404],"iteration":408,"passed_time":5.082182814,"remaining_time":7.343692037},
{"learn":[0.152252004],"iteration":409,"passed_time":5.093491711,"remaining_time":7.329658804},
{"learn":[0.1521574873],"iteration":410,"passed_time":5.105119057,"remaining_time":7.316095194},
{"learn":[0.152142272],"iteration":411,"passed_time":5.115387438,"remaining_time":7.30060149},
{"learn":[0.1520401177],"iteration":412,"passed_time":5.127027868,"remaining_time":7.287083193},
{"learn":[0.1519949675],"iteration":413,"passed_time":5.137841108,"remaining_time":7.272403114},
{"learn":[0.1519723774],"iteration":414,"passed_time":5.148394346,"remaining_time":7.257375163},
{"learn":[0.1519526813],"iteration":415,"passed_time":5.160523591,"remaining_time":7.244581195},
{"learn":[0.1519337421],"iteration":416,"passed_time":5.171800118,"remaining_time":7.230598246},
{"learn":[0.1519225815],"iteration":417,"passed_time":5.182188902,"remaining_time":7.215392203},
{"learn":[0.1518904192],"iteration":418,"passed_time":5.192949193,"remaining_time":7.200724299},
{"learn":[0.1518552718],"iteration":419,"passed_time":5.203095068,"remaining_time":7.185226523},
{"learn":[0.1518271324],"iteration":420,"passed_time":5.213899732,"remaining_time":7.170660201},
{"learn":[0.1517469162],"iteration":421,"passed_time":5.22501475,"remaining_time":7.15653679},
{"learn":[0.1516925558],"iteration":422,"passed_time":5.236481889,"remaining_time":7.14290792},
{"learn":[0.1516506103],"iteration":423,"passed_time":5.247517801,"remaining_time":7.128703427},
{"learn":[0.1516186047],"iteration":424,"passed_time":5.259992304,"remaining_time":7.116460176},
{"learn":[0.1515420437],"iteration":425,"passed_time":5.2734676,"remaining_time":7.105564325},
{"learn":[0.1514535245],"iteration":426,"passed_time":5.292520036,"remaining_time":7.102140469},
{"learn":[0.151429403],"iteration":427,"passed_time":5.302492339,"remaining_time":7.086508453},
{"learn":[0.1513783472],"iteration":428,"passed_time":5.314612066,"remaining_time":7.073761048},
{"learn":[0.1513579634],"iteration":429,"passed_time":5.32491405,"remaining_time":7.058606996},
{"learn":[0.1513101319],"iteration":430,"passed_time":5.340433788,"remaining_time":7.050363864},
{"learn":[0.1512546878],"iteration":431,"passed_time":5.351233433,"remaining_time":7.035880995},
{"learn":[0.1512029482],"iteration":432,"passed_time":5.364209995,"remaining_time":7.024265744},
{"learn":[0.1511667301],"iteration":433,"passed_time":5.378684861,"remaining_time":7.014598228},
{"learn":[0.1511274195],"iteration":434,"passed_time":5.390963792,"remaining_time":7.00205642},
{"learn":[0.1510924412],"iteration":435,"passed_time":5.404150854,"remaining_time":6.990690555},
{"learn":[0.1510071342],"iteration":436,"passed_time":5.41576189,"remaining_time":6.977285914},
{"learn":[0.1509791534],"iteration":437,"passed_time":5.426350795,"remaining_time":6.96257796},
{"learn":[0.1509426398],"iteration":438,"passed_time":5.437948456,"remaining_time":6.949177867},
{"learn":[0.1509065504],"iteration":439,"passed_time":5.450153811,"remaining_time":6.936559396},
{"learn":[0.1508309779],"iteration":440,"passed_time":5.464842362,"remaining_time":6.927090432},
{"learn":[0.1508077817],"iteration":441,"passed_time":5.476736632,"remaining_time":6.914070227},
{"learn":[0.150753395],"iteration":442,"passed_time":5.488142207,"remaining_time":6.900440654},
{"learn":[0.1506642031],"iteration":443,"passed_time":5.499752001,"remaining_time":6.88707683},
{"learn":[0.1505736698],"iteration":444,"passed_time":5.510946716,"remaining_time":6.873203208},
{"learn":[0.1505302748],"iteration":445,"passed_time":5.524705887,"remaining_time":6.862527044},
{"learn":[0.1505023307],"iteration":446,"passed_time":5.535899521,"remaining_time":6.848663165},
{"learn":[0.1504676451],"iteration":447,"passed_time":5.546747003,"remaining_time":6.834384701},
{"learn":[0.1504470259],"iteration":448,"passed_time":5.560769512,"remaining_time":6.824017819},
{"learn":[0.1504046568],"iteration":449,"passed_time":5.573114986,"remaining_time":6.811584983},
{"learn":[0.1503628436],"iteration":450,"passed_time":5.584525742,"remaining_time":6.798014705},
{"learn":[0.1503541249],"iteration":451,"passed_time":5.594669232,"remaining_time":6.782917564},
{"learn":[0.1503008158],"iteration":452,"passed_time":5.605809607,"remaining_time":6.769046037},
{"learn":[0.1502754018],"iteration":453,"passed_time":5.616583063,"remaining_time":6.754745269},
{"learn":[0.1502361602],"iteration":454,"passed_time":5.628851936,"remaining_time":6.74225122},
{"learn":[0.1501677905],"iteration":455,"passed_time":5.64045125,"remaining_time":6.728959386},
{"learn":[0.1501648515],"iteration":456,"passed_time":5.650321895,"remaining_time":6.713620982},
{"learn":[0.1501226443],"iteration":457,"passed_time":5.664060187,"remaining_time":6.702883453},
{"learn":[0.1500783445],"iteration":458,"passed_time":5.676137295,"remaining_time":6.690174895},
{"learn":[0.1500370566],"iteration":459,"passed_time":5.68759619,"remaining_time":6.676743353},
{"learn":[0.1499974362],"iteration":460,"passed_time":5.698205853,"remaining_time":6.66232745},
{"learn":[0.1499689937],"iteration":461,"passed_time":5.708623821,"remaining_time":6.647704795},
{"learn":[0.1499233292],"iteration":462,"passed_time":5.720101319,"remaining_time":6.634329176},
{"learn":[0.1499054284],"iteration":463,"passed_time":5.730679344,"remaining_time":6.61992269},
{"learn":[0.1497461929],"iteration":464,"passed_time":5.742957283,"remaining_time":6.607488487},
{"learn":[0.1496990459],"iteration":465,"passed_time":5.759720914,"remaining_time":6.60019521},
{"learn":[0.1496326325],"iteration":466,"passed_time":5.77846528,"remaining_time":6.595122043},
{"learn":[0.1495888034],"iteration":467,"passed_time":5.791378064,"remaining_time":6.583361389},
{"learn":[0.1495650846],"iteration":468,"passed_time":5.802833051,"remaining_time":6.56994531},
{"learn":[0.1494929981],"iteration":469,"passed_time":5.814518485,"remaining_time":6.55679744},
{"learn":[0.1494377484],"iteration":470,"passed_time":5.825995843,"remaining_time":6.543422083},
{"learn":[0.1493499337],"iteration":471,"passed_time":5.83749411,"remaining_time":6.530078157},
{"learn":[0.1493302968],"iteration":472,"passed_time":5.848195132,"remaining_time":6.515853773},
{"learn":[0.1492984812],"iteration":473,"passed_time":5.862699742,"remaining_time":6.505865115},
{"learn":[0.1492565987],"iteration":474,"passed_time":5.874535674,"remaining_time":6.492907851},
{"learn":[0.1492547193],"iteration":475,"passed_time":5.885311956,"remaining_time":6.478788791},
{"learn":[0.1492107207],"iteration":476,"passed_time":5.897314736,"remaining_time":6.466028526},
{"learn":[0.1491610394],"iteration":477,"passed_time":5.909191564,"remaining_time":6.453133884},
{"learn":[0.1491388093],"iteration":478,"passed_time":5.920133161,"remaining_time":6.439226256},
{"learn":[0.1490912026],"iteration":479,"passed_time":5.93720967,"remaining_time":6.431977143},
{"learn":[0.1490499697],"iteration":480,"passed_time":5.949745217,"remaining_time":6.419787459},
{"learn":[0.149019495],"iteration":481,"passed_time":5.960174015,"remaining_time":6.40533224},
{"learn":[0.1489516766],"iteration":482,"passed_time":5.97494048,"remaining_time":6.395536704},
{"learn":[0.1489197602],"iteration":483,"passed_time":5.986525488,"remaining_time":6.382328826},
{"learn":[0.1488817034],"iteration":484,"passed_time":5.997552012,"remaining_time":6.36853461},
{"learn":[0.1488236416],"iteration":485,"passed_time":6.00868882,"remaining_time":6.354868423},
{"learn":[0.1487950814],"iteration":486,"passed_time":6.021289788,"remaining_time":6.342754951},
{"learn":[0.1487665703],"iteration":487,"passed_time":6.031896876,"remaining_time":6.328547542},
{"learn":[0.1487456173],"iteration":488,"passed_time":6.042866805,"remaining_time":6.314734023},
{"learn":[0.1487158037],"iteration":489,"passed_time":6.056975883,"remaining_time":6.304199389},
{"learn":[0.1486818072],"iteration":490,"passed_time":6.068850808,"remaining_time":6.291334137},
{"learn":[0.1486376976],"iteration":491,"passed_time":6.080067423,"remaining_time":6.277793193},
{"learn":[0.1486015328],"iteration":492,"passed_time":6.091617777,"remaining_time":6.264604894},
{"learn":[0.1485587712],"iteration":493,"passed_time":6.103671171,"remaining_time":6.251938487},
{"learn":[0.1485141503],"iteration":494,"passed_time":6.115154491,"remaining_time":6.238692965},
{"learn":[0.1484756362],"iteration":495,"passed_time":6.126608256,"remaining_time":6.225424518},
{"learn":[0.1484362069],"iteration":496,"passed_time":6.138374839,"remaining_time":6.212479968},
{"learn":[0.1483817371],"iteration":497,"passed_time":6.152399321,"remaining_time":6.201816183},
{"learn":[0.1483810019],"iteration":498,"passed_time":6.161602421,"remaining_time":6.186298222},
{"learn":[0.1483610517],"iteration":499,"passed_time":6.172651377,"remaining_time":6.172651377},
{"learn":[0.1483371417],"iteration":500,"passed_time":6.184713066,"remaining_time":6.160023593},
{"learn":[0.1482515257],"iteration":501,"passed_time":6.196223416,"remaining_time":6.146851118},
{"learn":[0.1482193709],"iteration":502,"passed_time":6.20775799,"remaining_time":6.133709187},
{"learn":[0.1481837473],"iteration":503,"passed_time":6.219054845,"remaining_time":6.120339688},
{"learn":[0.1481598312],"iteration":504,"passed_time":6.230192014,"remaining_time":6.106821875},
{"learn":[0.1481311417],"iteration":505,"passed_time":6.241521669,"remaining_time":6.093501392},
{"learn":[0.1481143164],"iteration":506,"passed_time":6.254750638,"remaining_time":6.082035631},
{"learn":[0.1480601848],"iteration":507,"passed_time":6.269641383,"remaining_time":6.072172363},
{"learn":[0.1480227268],"iteration":508,"passed_time":6.284113914,"remaining_time":6.061885917},
{"learn":[0.147966243],"iteration":509,"passed_time":6.296399648,"remaining_time":6.049482015},
{"learn":[0.1479140358],"iteration":510,"passed_time":6.307602509,"remaining_time":6.036042323},
{"learn":[0.1478806378],"iteration":511,"passed_time":6.319188288,"remaining_time":6.022976337},
{"learn":[0.1478464326],"iteration":512,"passed_time":6.330688188,"remaining_time":6.009834596},
{"learn":[0.147801053],"iteration":513,"passed_time":6.341964254,"remaining_time":5.996487602},
{"learn":[0.1477530948],"iteration":514,"passed_time":6.356280245,"remaining_time":5.986011493},
{"learn":[0.1477085443],"iteration":515,"passed_time":6.367652599,"remaining_time":5.972759415},
{"learn":[0.1476489547],"iteration":516,"passed_time":6.378676819,"remaining_time":5.959189369},
{"learn":[0.1476294314],"iteration":517,"passed_time":6.389790996,"remaining_time":5.945712857},
{"learn":[0.1476078995],"iteration":518,"passed_time":6.400272401,"remaining_time":5.931659008},
{"learn":[0.1475457596],"iteration":519,"passed_time":6.412497613,"remaining_time":5.919228566},
{"learn":[0.1475259067],"iteration":520,"passed_time":6.422716984,"remaining_time":5.90495477},
{"learn":[0.1474982406],"iteration":521,"passed_time":6.433940543,"remaining_time":5.891616053},
{"learn":[0.1474403744],"iteration":522,"passed_time":6.447452516,"remaining_time":5.880372563},
{"learn":[0.1474132644],"iteration":523,"passed_time":6.459061648,"remaining_time":5.867391879},
{"learn":[0.1473914188],"iteration":524,"passed_time":6.469944066,"remaining_time":5.853758917},
{"learn":[0.1473453166],"iteration":525,"passed_time":6.481955272,"remaining_time":5.84115361},
{"learn":[0.1472980146],"iteration":526,"passed_time":6.492642629,"remaining_time":5.827362359},
{"learn":[0.1472488939],"iteration":527,"passed_time":6.503477629,"remaining_time":5.81371485},
{"learn":[0.1472149443],"iteration":528,"passed_time":6.515542374,"remaining_time":5.801172889},
{"learn":[0.147186047],"iteration":529,"passed_time":6.531777156,"remaining_time":5.792330685},
{"learn":[0.1471491205],"iteration":530,"passed_time":6.54447868,"remaining_time":5.780339926},
{"learn":[0.1471090393],"iteration":531,"passed_time":6.555884415,"remaining_time":5.767206591},
{"learn":[0.1470804363],"iteration":532,"passed_time":6.569787883,"remaining_time":5.756268183},
{"learn":[0.1470632265],"iteration":533,"passed_time":6.581025678,"remaining_time":5.742992446},
{"learn":[0.1470072998],"iteration":534,"passed_time":6.592017829,"remaining_time":5.729510823},
{"learn":[0.1469601389],"iteration":535,"passed_time":6.603438583,"remaining_time":5.716409519},
{"learn":[0.1469075322],"iteration":536,"passed_time":6.614286997,"remaining_time":5.702821005},
{"learn":[0.1468785332],"iteration":537,"passed_time":6.625618957,"remaining_time":5.689657915},
{"learn":[0.1468205695],"iteration":538,"passed_time":6.637379199,"remaining_time":5.676867923},
{"learn":[0.1467801702],"iteration":539,"passed_time":6.651040458,"remaining_time":5.665701131},
{"learn":[0.1467390106],"iteration":540,"passed_time":6.664017522,"remaining_time":5.653944626},
{"learn":[0.1467129423],"iteration":541,"passed_time":6.675086645,"remaining_time":5.640571372},
{"learn":[0.1466876732],"iteration":542,"passed_time":6.686002865,"remaining_time":5.627077918},
{"learn":[0.1466507962],"iteration":543,"passed_time":6.697250218,"remaining_time":5.613871506},
{"learn":[0.1465920773],"iteration":544,"passed_time":6.707853769,"remaining_time":5.600134798},
{"learn":[0.1465504434],"iteration":545,"passed_time":6.718665807,"remaining_time":5.586582923},
{"learn":[0.1465024991],"iteration":546,"passed_time":6.729912238,"remaining_time":5.573400811},
{"learn":[0.1464784018],"iteration":547,"passed_time":6.743402701,"remaining_time":5.562076681},
{"learn":[0.1464465081],"iteration":548,"passed_time":6.755774876,"remaining_time":5.549825991},
{"learn":[0.1464174945],"iteration":549,"passed_time":6.772816771,"remaining_time":5.54139554},
{"learn":[0.1463495454],"iteration":550,"passed_time":6.7849753,"remaining_time":5.528954464},
{"learn":[0.1463124804],"iteration":551,"passed_time":6.797268638,"remaining_time":5.516623822},
{"learn":[0.1463003219],"iteration":552,"passed_time":6.807244097,"remaining_time":5.502419732},
{"learn":[0.1462760767],"iteration":553,"passed_time":6.817627071,"remaining_time":5.488558978},
{"learn":[0.1462643463],"iteration":554,"passed_time":6.827969509,"remaining_time":5.474678255},
{"learn":[0.1462127717],"iteration":555,"passed_time":6.84377663,"remaining_time":5.465174143},
{"learn":[0.1461812399],"iteration":556,"passed_time":6.860529861,"remaining_time":5.456399871},
{"learn":[0.1461267165],"iteration":557,"passed_time":6.875277491,"remaining_time":5.446008335},
{"learn":[0.1460635145],"iteration":558,"passed_time":6.891432766,"remaining_time":5.436711717},
{"learn":[0.1460268544],"iteration":559,"passed_time":6.908107772,"remaining_time":5.427798964},
{"learn":[0.1459826174],"iteration":560,"passed_time":6.925873797,"remaining_time":5.419712294},
{"learn":[0.1459271547],"iteration":561,"passed_time":6.942750066,"remaining_time":5.410897739},
{"learn":[0.1459097698],"iteration":562,"passed_time":6.956289881,"remaining_time":5.399464792},
{"learn":[0.1458670849],"iteration":563,"passed_time":6.967898513,"remaining_time":5.386531474},
{"learn":[0.1458210748],"iteration":564,"passed_time":6.98101286,"remaining_time":5.374762114},
{"learn":[0.1458012311],"iteration":565,"passed_time":6.992329792,"remaining_time":5.36160977},
{"learn":[0.1457742463],"iteration":566,"passed_time":7.0039689,"remaining_time":5.348709936},
{"learn":[0.1457415871],"iteration":567,"passed_time":7.01629018,"remaining_time":5.336333376},
{"learn":[0.145730731],"iteration":568,"passed_time":7.026781594,"remaining_time":5.322570943},
{"learn":[0.1456849854],"iteration":569,"passed_time":7.041666988,"remaining_time":5.312134746},
{"learn":[0.1456588194],"iteration":570,"passed_time":7.052847668,"remaining_time":5.298899561},
{"learn":[0.1456254504],"iteration":571,"passed_time":7.063290462,"remaining_time":5.285119437},
{"learn":[0.1454743869],"iteration":572,"passed_time":7.075461855,"remaining_time":5.272639113},
{"learn":[0.1454562459],"iteration":573,"passed_time":7.086311762,"remaining_time":5.259179113},
{"learn":[0.1453942685],"iteration":574,"passed_time":7.097820298,"remaining_time":5.246215003},
{"learn":[0.1453506498],"iteration":575,"passed_time":7.109039839,"remaining_time":5.233043215},
{"learn":[0.1453169833],"iteration":576,"passed_time":7.125710488,"remaining_time":5.223874413},
{"learn":[0.1452855976],"iteration":577,"passed_time":7.138128467,"remaining_time":5.211574763},
{"learn":[0.1452468241],"iteration":578,"passed_time":7.150333742,"remaining_time":5.199120044},
{"learn":[0.1452069803],"iteration":579,"passed_time":7.161592496,"remaining_time":5.185980773},
{"learn":[0.1451386532],"iteration":580,"passed_time":7.173248906,"remaining_time":5.173134753},
{"learn":[0.1451132764],"iteration":581,"passed_time":7.183707289,"remaining_time":5.159432383},
{"learn":[0.1450829629],"iteration":582,"passed_time":7.195775581,"remaining_time":5.146892654},
{"learn":[0.1450608528],"iteration":583,"passed_time":7.207414568,"remaining_time":5.134048734},
{"learn":[0.1449991277],"iteration":584,"passed_time":7.219357919,"remaining_time":5.121424849},
{"learn":[0.1449514295],"iteration":585,"passed_time":7.230295248,"remaining_time":5.108092547},
{"learn":[0.1449412485],"iteration":586,"passed_time":7.244191673,"remaining_time":5.096850359},
{"learn":[0.1449042948],"iteration":587,"passed_time":7.261516552,"remaining_time":5.088001394},
{"learn":[0.1448518212],"iteration":588,"passed_time":7.273318912,"remaining_time":5.075270073},
{"learn":[0.144826808],"iteration":589,"passed_time":7.284332162,"remaining_time":5.061993536},
{"learn":[0.1446985918],"iteration":590,"passed_time":7.296039586,"remaining_time":5.04920506},
{"learn":[0.1446590615],"iteration":591,"passed_time":7.306761626,"remaining_time":5.035741121},
{"learn":[0.1446264306],"iteration":592,"passed_time":7.317568554,"remaining_time":5.022344691},
{"learn":[0.1445858829],"iteration":593,"passed_time":7.328313317,"remaining_time":5.008914489},
{"learn":[0.1445447671],"iteration":594,"passed_time":7.342190687,"remaining_time":4.997625593},
{"learn":[0.1445092803],"iteration":595,"passed_time":7.353971517,"remaining_time":4.984906867},
{"learn":[0.1444705586],"iteration":596,"passed_time":7.365385358,"remaining_time":4.97194355},
{"learn":[0.1444416803],"iteration":597,"passed_time":7.377288554,"remaining_time":4.959314379},
{"learn":[0.1444132689],"iteration":598,"passed_time":7.388069153,"remaining_time":4.945936111},
{"learn":[0.1444007768],"iteration":599,"passed_time":7.398483665,"remaining_time":4.932322443},
{"learn":[0.1443705587],"iteration":600,"passed_time":7.410547749,"remaining_time":4.919814562},
{"learn":[0.1443552792],"iteration":601,"passed_time":7.421609368,"remaining_time":4.906645396},
{"learn":[0.1443502104],"iteration":602,"passed_time":7.43287253,"remaining_time":4.893615911},
{"learn":[0.1442897745],"iteration":603,"passed_time":7.446686843,"remaining_time":4.882264884},
{"learn":[0.1442892493],"iteration":604,"passed_time":7.455596951,"remaining_time":4.867703794},
{"learn":[0.1442521955],"iteration":605,"passed_time":7.466744258,"remaining_time":4.854615904},
{"learn":[0.1442277253],"iteration":606,"passed_time":7.477730799,"remaining_time":4.841430319},
{"learn":[0.1441959675],"iteration":607,"passed_time":7.48850197,"remaining_time":4.828113112},
{"learn":[0.1441767442],"iteration":608,"passed_time":7.500534336,"remaining_time":4.815613999},
{"learn":[0.1441343277],"iteration":609,"passed_time":7.511418737,"remaining_time":4.802382471},
{"learn":[0.1441060864],"iteration":610,"passed_time":7.522356807,"remaining_time":4.789192796},
{"learn":[0.144068333],"iteration":611,"passed_time":7.535583884,"remaining_time":4.777461678},
{"learn":[0.1440475023],"iteration":612,"passed_time":7.547682412,"remaining_time":4.765013203},
{"learn":[0.1440116081],"iteration":613,"passed_time":7.55934904,"remaining_time":4.752294348},
{"learn":[0.1439798261],"iteration":614,"passed_time":7.570515103,"remaining_time":4.739265552},
{"learn":[0.1439397001],"iteration":615,"passed_time":7.581316931,"remaining_time":4.726015749},
{"learn":[0.1439067892],"iteration":616,"passed_time":7.592057346,"remaining_time":4.712735759},
{"learn":[0.1438736368],"iteration":617,"passed_time":7.604096023,"remaining_time":4.700266474},
{"learn":[0.1438307929],"iteration":618,"passed_time":7.616141733,"remaining_time":4.687802908},
{"learn":[0.1437978776],"iteration":619,"passed_time":7.628794376,"remaining_time":4.675712682},
{"learn":[0.1437680222],"iteration":620,"passed_time":7.642511028,"remaining_time":4.664270016},
{"learn":[0.1437332443],"iteration":621,"passed_time":7.654221328,"remaining_time":4.651600743},
{"learn":[0.1437113064],"iteration":622,"passed_time":7.66581958,"remaining_time":4.638866744},
{"learn":[0.1436841185],"iteration":623,"passed_time":7.677578189,"remaining_time":4.626233011},
{"learn":[0.143617356],"iteration":624,"passed_time":7.689260126,"remaining_time":4.613556076},
{"learn":[0.1435977171],"iteration":625,"passed_time":7.706754338,"remaining_time":4.604354828},
{"learn":[0.1435776114],"iteration":626,"passed_time":7.723716015,"remaining_time":4.594810325},
{"learn":[0.1435529497],"iteration":627,"passed_time":7.743201603,"remaining_time":4.586737255},
{"learn":[0.1435100134],"iteration":628,"passed_time":7.761154173,"remaining_time":4.577723686},
{"learn":[0.1434704464],"iteration":629,"passed_time":7.775290793,"remaining_time":4.566440624},
{"learn":[0.1434375818],"iteration":630,"passed_time":7.786715804,"remaining_time":4.553562808},
{"learn":[0.1434119254],"iteration":631,"passed_time":7.797552096,"remaining_time":4.54034679},
{"learn":[0.1433622048],"iteration":632,"passed_time":7.808752582,"remaining_time":4.527349444},
{"learn":[0.1433389187],"iteration":633,"passed_time":7.819939734,"remaining_time":4.514350067},
{"learn":[0.1432945812],"iteration":634,"passed_time":7.833135973,"remaining_time":4.502511229},
{"learn":[0.1432581003],"iteration":635,"passed_time":7.84594213,"remaining_time":4.490444867},
{"learn":[0.1432423253],"iteration":636,"passed_time":7.856897563,"remaining_time":4.477321531},
{"learn":[0.1432196741],"iteration":637,"passed_time":7.86761765,"remaining_time":4.464071457},
{"learn":[0.1431882149],"iteration":638,"passed_time":7.87909035,"remaining_time":4.451254486},
{"learn":[0.1431412582],"iteration":639,"passed_time":7.8902876,"remaining_time":4.438286775},
{"learn":[0.143108354],"iteration":640,"passed_time":7.90242536,"remaining_time":4.425851333},
{"learn":[0.1430814773],"iteration":641,"passed_time":7.91434125,"remaining_time":4.413293096},
{"learn":[0.1430371262],"iteration":642,"passed_time":7.925147838,"remaining_time":4.400120961},
{"learn":[0.1429646491],"iteration":643,"passed_time":7.93859956,"remaining_time":4.38841839},
{"learn":[0.1429179712],"iteration":644,"passed_time":7.95020224,"remaining_time":4.375692706},
{"learn":[0.142883564],"iteration":645,"passed_time":7.961370346,"remaining_time":4.362732357},
{"learn":[0.1428817659],"iteration":646,"passed_time":7.97153187,"remaining_time":4.349228362},
{"learn":[0.1428530697],"iteration":647,"passed_time":7.982771408,"remaining_time":4.336320271},
{"learn":[0.1428232112],"iteration":648,"passed_time":7.993875576,"remaining_time":4.32334411},
{"learn":[0.1427287891],"iteration":649,"passed_time":8.00704215,"remaining_time":4.311484235},
{"learn":[0.1426664373],"iteration":650,"passed_time":8.018962949,"remaining_time":4.298952487},
{"learn":[0.1426242965],"iteration":651,"passed_time":8.031838224,"remaining_time":4.286932058},
{"learn":[0.1425812219],"iteration":652,"passed_time":8.044499023,"remaining_time":4.27479504},
{"learn":[0.1425400886],"iteration":653,"passed_time":8.056720478,"remaining_time":4.262423984},
{"learn":[0.142505821],"iteration":654,"passed_time":8.068445645,"remaining_time":4.249791981},
{"learn":[0.1424646486],"iteration":655,"passed_time":8.079982494,"remaining_time":4.23706399},
{"learn":[0.1424283705],"iteration":656,"passed_time":8.090708762,"remaining_time":4.223916447},
{"learn":[0.1423981947],"iteration":657,"passed_time":8.101593905,"remaining_time":4.210858838},
{"learn":[0.1423736005],"iteration":658,"passed_time":8.113843242,"remaining_time":4.198513726},
{"learn":[0.1423290252],"iteration":659,"passed_time":8.124516292,"remaining_time":4.185356878},
{"learn":[0.1422800753],"iteration":660,"passed_time":8.139680773,"remaining_time":4.174511017},
{"learn":[0.1422261108],"iteration":661,"passed_time":8.151423142,"remaining_time":4.161904867},
{"learn":[0.1421692424],"iteration":662,"passed_time":8.163276606,"remaining_time":4.149357792},
{"learn":[0.1421281951],"iteration":663,"passed_time":8.174812653,"remaining_time":4.136652186},
{"learn":[0.1421090403],"iteration":664,"passed_time":8.185603672,"remaining_time":4.123574782},
{"learn":[0.1420782317],"iteration":665,"passed_time":8.19800512,"remaining_time":4.111311877},
{"learn":[0.1420506824],"iteration":666,"passed_time":8.209700863,"remaining_time":4.098696233},
{"learn":[0.1419991996],"iteration":667,"passed_time":8.221284578,"remaining_time":4.086027664},
{"learn":[0.1419450541],"iteration":668,"passed_time":8.233429972,"remaining_time":4.07364024},
{"learn":[0.1418990044],"iteration":669,"passed_time":8.247523071,"remaining_time":4.062212856},
{"learn":[0.1418658325],"iteration":670,"passed_time":8.261807354,"remaining_time":4.050871266},
{"learn":[0.1418372213],"iteration":671,"passed_time":8.272763207,"remaining_time":4.037896327},
{"learn":[0.141795303],"iteration":672,"passed_time":8.283677193,"remaining_time":4.024907046},
{"learn":[0.1417706149],"iteration":673,"passed_time":8.294385519,"remaining_time":4.01182445},
{"learn":[0.1417260786],"iteration":674,"passed_time":8.306228594,"remaining_time":3.999295249},
{"learn":[0.1416837451],"iteration":675,"passed_time":8.32212535,"remaining_time":3.988710967},
{"learn":[0.1416530095],"iteration":676,"passed_time":8.335277938,"remaining_time":3.976801734},
{"learn":[0.1416197485],"iteration":677,"passed_time":8.346636958,"remaining_time":3.964037021},
{"learn":[0.1415917712],"iteration":678,"passed_time":8.357869253,"remaining_time":3.951216539},
{"learn":[0.1415614346],"iteration":679,"passed_time":8.368777719,"remaining_time":3.938248338},
{"learn":[0.1415351064],"iteration":680,"passed_time":8.380325537,"remaining_time":3.925585678},
{"learn":[0.1414892031],"iteration":681,"passed_time":8.391641868,"remaining_time":3.912818349},
{"learn":[0.1414503478],"iteration":682,"passed_time":8.403305922,"remaining_time":3.900216658},
{"learn":[0.1414245073],"iteration":683,"passed_time":8.413912258,"remaining_time":3.887129055},
{"learn":[0.1414075783],"iteration":684,"passed_time":8.424962286,"remaining_time":3.87425273},
{"learn":[0.1413691249],"iteration":685,"passed_time":8.438573323,"remaining_time":3.86255397},
{"learn":[0.1413392417],"iteration":686,"passed_time":8.449735959,"remaining_time":3.849734141},
{"learn":[0.1413138357],"iteration":687,"passed_time":8.461424097,"remaining_time":3.837157439},
{"learn":[0.1412787663],"iteration":688,"passed_time":8.473196622,"remaining_time":3.824621407},
{"learn":[0.1412258159],"iteration":689,"passed_time":8.484480001,"remaining_time":3.811867827},
{"learn":[0.1412006804],"iteration":690,"passed_time":8.496255782,"remaining_time":3.799338693},
{"learn":[0.1411908923],"iteration":691,"passed_time":8.508809773,"remaining_time":3.787158107},
{"learn":[0.1411572076],"iteration":692,"passed_time":8.521259501,"remaining_time":3.774930255},
{"learn":[0.1411228674],"iteration":693,"passed_time":8.538263245,"remaining_time":3.764709731},
{"learn":[0.141081059],"iteration":694,"passed_time":8.550488949,"remaining_time":3.752372848},
{"learn":[0.1410449871],"iteration":695,"passed_time":8.561415017,"remaining_time":3.739468628},
{"learn":[0.1410106601],"iteration":696,"passed_time":8.572328873,"remaining_time":3.726564775},
{"learn":[0.1409709612],"iteration":697,"passed_time":8.583438961,"remaining_time":3.713751528},
{"learn":[0.1409382359],"iteration":698,"passed_time":8.594601888,"remaining_time":3.700965906},
{"learn":[0.1409047142],"iteration":699,"passed_time":8.605704222,"remaining_time":3.688158952},
{"learn":[0.1408711885],"iteration":700,"passed_time":8.616709137,"remaining_time":3.675315309},
{"learn":[0.1408410863],"iteration":701,"passed_time":8.630626941,"remaining_time":3.663713431},
{"learn":[0.1408082215],"iteration":702,"passed_time":8.643642225,"remaining_time":3.651723671},
{"learn":[0.1407701559],"iteration":703,"passed_time":8.655429617,"remaining_time":3.639214726},
{"learn":[0.1407292013],"iteration":704,"passed_time":8.666539726,"remaining_time":3.626424424},
{"learn":[0.1406977251],"iteration":705,"passed_time":8.678097123,"remaining_time":3.613825147},
{"learn":[0.1406595297],"iteration":706,"passed_time":8.689050652,"remaining_time":3.600978559},
{"learn":[0.1406301288],"iteration":707,"passed_time":8.700329072,"remaining_time":3.588271312},
{"learn":[0.1405956973],"iteration":708,"passed_time":8.711525661,"remaining_time":3.57553451},
{"learn":[0.1405630243],"iteration":709,"passed_time":8.726012929,"remaining_time":3.564146126},
{"learn":[0.1405514806],"iteration":710,"passed_time":8.740310757,"remaining_time":3.552672024},
{"learn":[0.1405224386],"iteration":711,"passed_time":8.752093761,"remaining_time":3.540172757},
{"learn":[0.140496354],"iteration":712,"passed_time":8.764221874,"remaining_time":3.527814415},
{"learn":[0.1404634117],"iteration":713,"passed_time":8.775825987,"remaining_time":3.515246824},
{"learn":[0.1404291494],"iteration":714,"passed_time":8.787080553,"remaining_time":3.502542598},
{"learn":[0.1403887108],"iteration":715,"passed_time":8.798455963,"remaining_time":3.489890354},
{"learn":[0.1403675489],"iteration":716,"passed_time":8.808810784,"remaining_time":3.476838845},
{"learn":[0.140344467],"iteration":717,"passed_time":8.820755687,"remaining_time":3.464419365},
{"learn":[0.1402926104],"iteration":718,"passed_time":8.834363057,"remaining_time":3.452650931},
{"learn":[0.140244625],"iteration":719,"passed_time":8.846051396,"remaining_time":3.440131098},
{"learn":[0.1402136465],"iteration":720,"passed_time":8.857774299,"remaining_time":3.427626948},
{"learn":[0.1401757892],"iteration":721,"passed_time":8.869266124,"remaining_time":3.415035987},
{"learn":[0.1401507192],"iteration":722,"passed_time":8.881348402,"remaining_time":3.402674284},
{"learn":[0.1401197543],"iteration":723,"passed_time":8.892284268,"remaining_time":3.389876323},
{"learn":[0.1400916039],"iteration":724,"passed_time":8.903461401,"remaining_time":3.377175014},
{"learn":[0.1400655565],"iteration":725,"passed_time":8.91861896,"remaining_time":3.365980158},
{"learn":[0.1399995773],"iteration":726,"passed_time":8.93352368,"remaining_time":3.354679456},
{"learn":[0.1399606831],"iteration":727,"passed_time":8.945791862,"remaining_time":3.342383773},
{"learn":[0.1399211882],"iteration":728,"passed_time":8.958083507,"remaining_time":3.330096887},
{"learn":[0.139883476],"iteration":729,"passed_time":8.970864578,"remaining_time":3.317991008},
{"learn":[0.1398418402],"iteration":730,"passed_time":8.981890762,"remaining_time":3.305237503},
{"learn":[0.1398083076],"iteration":731,"passed_time":8.993201292,"remaining_time":3.292592823},
{"learn":[0.1397849952],"iteration":732,"passed_time":9.004129304,"remaining_time":3.279812448},
{"learn":[0.1397604816],"iteration":733,"passed_time":9.017049983,"remaining_time":3.267759258},
{"learn":[0.1397241508],"iteration":734,"passed_time":9.031050701,"remaining_time":3.25609311},
{"learn":[0.1396943699],"iteration":735,"passed_time":9.042629046,"remaining_time":3.243551723},
{"learn":[0.1396673428],"iteration":736,"passed_time":9.054181133,"remaining_time":3.231003579},
{"learn":[0.1396384854],"iteration":737,"passed_time":9.065256237,"remaining_time":3.218288799},
{"learn":[0.1396236884],"iteration":738,"passed_time":9.076076108,"remaining_time":3.205488314},
{"learn":[0.1396049243],"iteration":739,"passed_time":9.086892303,"remaining_time":3.19269189},
{"learn":[0.1395735877],"iteration":740,"passed_time":9.097752891,"remaining_time":3.179916327},
{"learn":[0.1395306029],"iteration":741,"passed_time":9.10837709,"remaining_time":3.167063732},
{"learn":[0.1394992487],"iteration":742,"passed_time":9.120666441,"remaining_time":3.154793103},
{"learn":[0.1394604182],"iteration":743,"passed_time":9.133694509,"remaining_time":3.142776605},
{"learn":[0.1394080854],"iteration":744,"passed_time":9.1454598,"remaining_time":3.130325167},
{"learn":[0.1393995576],"iteration":745,"passed_time":9.156492115,"remaining_time":3.117626002},
{"learn":[0.1393705254],"iteration":746,"passed_time":9.167905806,"remaining_time":3.105060467},
{"learn":[0.139281169],"iteration":747,"passed_time":9.179113535,"remaining_time":3.092428624},
{"learn":[0.1392654077],"iteration":748,"passed_time":9.189352953,"remaining_time":3.07947609},
{"learn":[0.1392336905],"iteration":749,"passed_time":9.201471037,"remaining_time":3.067157012},
{"learn":[0.1392019124],"iteration":750,"passed_time":9.214038593,"remaining_time":3.054987496},
{"learn":[0.1391768138],"iteration":751,"passed_time":9.231468837,"remaining_time":3.044420574},
{"learn":[0.1391356142],"iteration":752,"passed_time":9.244330547,"remaining_time":3.032336846},
{"learn":[0.1391070012],"iteration":753,"passed_time":9.255897742,"remaining_time":3.019828706},
{"learn":[0.1390772991],"iteration":754,"passed_time":9.267243377,"remaining_time":3.007251162},
{"learn":[0.1390464201],"iteration":755,"passed_time":9.278301249,"remaining_time":2.994584001},
{"learn":[0.1390144169],"iteration":756,"passed_time":9.28981808,"remaining_time":2.982068419},
{"learn":[0.1389872475],"iteration":757,"passed_time":9.300438583,"remaining_time":2.96926931},
{"learn":[0.13895865],"iteration":758,"passed_time":9.313096817,"remaining_time":2.957122968},
{"learn":[0.1389151347],"iteration":759,"passed_time":9.327591989,"remaining_time":2.945555365},
{"learn":[0.1388927881],"iteration":760,"passed_time":9.338451925,"remaining_time":2.932838384},
{"learn":[0.1388837706],"iteration":761,"passed_time":9.34906784,"remaining_time":2.92005006},
{"learn":[0.1388600669],"iteration":762,"passed_time":9.360472844,"remaining_time":2.907512535},
{"learn":[0.1388167486],"iteration":763,"passed_time":9.372073892,"remaining_time":2.895038532},
{"learn":[0.1388164916],"iteration":764,"passed_time":9.380331151,"remaining_time":2.881539635},
{"learn":[0.1387866522],"iteration":765,"passed_time":9.391420311,"remaining_time":2.868919521},
{"learn":[0.138747214],"iteration":766,"passed_time":9.402640093,"remaining_time":2.856343079},
{"learn":[0.1387259546],"iteration":767,"passed_time":9.415401337,"remaining_time":2.844235821},
{"learn":[0.1387023452],"iteration":768,"passed_time":9.428018335,"remaining_time":2.832083531},
{"learn":[0.1386835417],"iteration":769,"passed_time":9.438630602,"remaining_time":2.819331219},
{"learn":[0.1386511966],"iteration":770,"passed_time":9.449270291,"remaining_time":2.806592603},
{"learn":[0.1386355946],"iteration":771,"passed_time":9.465007251,"remaining_time":2.795364836},
{"learn":[0.1386024368],"iteration":772,"passed_time":9.485669686,"remaining_time":2.785571823},
{"learn":[0.1385722855],"iteration":773,"passed_time":9.498463361,"remaining_time":2.773453126},
{"learn":[0.1385480286],"iteration":774,"passed_time":9.514192116,"remaining_time":2.762184808},
{"learn":[0.1385287694],"iteration":775,"passed_time":9.526502917,"remaining_time":2.749918368},
{"learn":[0.1385155927],"iteration":776,"passed_time":9.536927187,"remaining_time":2.737110377},
{"learn":[0.1384681364],"iteration":777,"passed_time":9.547916201,"remaining_time":2.724469662},
{"learn":[0.1384365075],"iteration":778,"passed_time":9.559369265,"remaining_time":2.711964836},
{"learn":[0.1384041086],"iteration":779,"passed_time":9.574451744,"remaining_time":2.700486389},
{"learn":[0.1383725195],"iteration":780,"passed_time":9.590353881,"remaining_time":2.689228553},
{"learn":[0.1383449932],"iteration":781,"passed_time":9.604969567,"remaining_time":2.677600212},
{"learn":[0.1383184121],"iteration":782,"passed_time":9.618763462,"remaining_time":2.665736489},
{"learn":[0.138271241],"iteration":783,"passed_time":9.630697054,"remaining_time":2.653355311},
{"learn":[0.1382375068],"iteration":784,"passed_time":9.641489255,"remaining_time":2.640662662},
{"learn":[0.1382125241],"iteration":785,"passed_time":9.652582062,"remaining_time":2.628056694},
{"learn":[0.1381769562],"iteration":786,"passed_time":9.664109012,"remaining_time":2.615572071},
{"learn":[0.1381326868],"iteration":787,"passed_time":9.675825623,"remaining_time":2.603140904},
{"learn":[0.1381015463],"iteration":788,"passed_time":9.689154307,"remaining_time":2.59114266},
{"learn":[0.1380941907],"iteration":789,"passed_time":9.702567428,"remaining_time":2.579163493},
{"learn":[0.1380540748],"iteration":790,"passed_time":9.719421896,"remaining_time":2.568089983},
{"learn":[0.1380214605],"iteration":791,"passed_time":9.73213957,"remaining_time":2.555915443},
{"learn":[0.137998285],"iteration":792,"passed_time":9.742268553,"remaining_time":2.543063796},
{"learn":[0.1379636463],"iteration":793,"passed_time":9.753526285,"remaining_time":2.530511857},
{"learn":[0.1379467937],"iteration":794,"passed_time":9.764922854,"remaining_time":2.517998975},
{"learn":[0.1379069991],"iteration":795,"passed_time":9.775924793,"remaining_time":2.505387761},
{"learn":[0.1378654751],"iteration":796,"passed_time":9.787461261,"remaining_time":2.492916733},
{"learn":[0.1378295304],"iteration":797,"passed_time":9.798659082,"remaining_time":2.480362324},
{"learn":[0.1377940637],"iteration":798,"passed_time":9.810000148,"remaining_time":2.467847346},
{"learn":[0.1377602016],"iteration":799,"passed_time":9.824106141,"remaining_time":2.456026535},
{"learn":[0.1377056267],"iteration":800,"passed_time":9.838724552,"remaining_time":2.444327323},
{"learn":[0.1376832756],"iteration":801,"passed_time":9.849844639,"remaining_time":2.431757155},
{"learn":[0.1376624438],"iteration":802,"passed_time":9.86049123,"remaining_time":2.419074436},
{"learn":[0.137630826],"iteration":803,"passed_time":9.87392585,"remaining_time":2.407076451},
{"learn":[0.1375837211],"iteration":804,"passed_time":9.885281223,"remaining_time":2.394571228},
{"learn":[0.1375332253],"iteration":805,"passed_time":9.896068895,"remaining_time":2.381932215},
{"learn":[0.1375162715],"iteration":806,"passed_time":9.907081043,"remaining_time":2.369351476},
{"learn":[0.1374956577],"iteration":807,"passed_time":9.92118402,"remaining_time":2.357509074},
{"learn":[0.1374820693],"iteration":808,"passed_time":9.931925116,"remaining_time":2.344867364},
{"learn":[0.1374281555],"iteration":809,"passed_time":9.943895747,"remaining_time":2.332518756},
{"learn":[0.1373978513],"iteration":810,"passed_time":9.954342088,"remaining_time":2.31981585},
{"learn":[0.1373627292],"iteration":811,"passed_time":9.965056574,"remaining_time":2.307180586},
{"learn":[0.1373128311],"iteration":812,"passed_time":9.976497796,"remaining_time":2.294717205},
{"learn":[0.1372930991],"iteration":813,"passed_time":9.987049952,"remaining_time":2.282053183},
{"learn":[0.1372667837],"iteration":814,"passed_time":10.00010407,"remaining_time":2.269962273},
{"learn":[0.1372308429],"iteration":815,"passed_time":10.01478418,"remaining_time":2.258235649},
{"learn":[0.1372080235],"iteration":816,"passed_time":10.02665782,"remaining_time":2.24587317},
{"learn":[0.1371706602],"iteration":817,"passed_time":10.03864599,"remaining_time":2.233537372},
{"learn":[0.1371459813],"iteration":818,"passed_time":10.04974589,"remaining_time":2.221006112},
{"learn":[0.1371009641],"iteration":819,"passed_time":10.06262118,"remaining_time":2.208868065},
{"learn":[0.1370526189],"iteration":820,"passed_time":10.07416543,"remaining_time":2.196438016},
{"learn":[0.137022951],"iteration":821,"passed_time":10.08527854,"remaining_time":2.183916764},
{"learn":[0.1369961276],"iteration":822,"passed_time":10.09957433,"remaining_time":2.172083423},
{"learn":[0.1369652873],"iteration":823,"passed_time":10.11513862,"remaining_time":2.160515044},
{"learn":[0.1369439923],"iteration":824,"passed_time":10.12699806,"remaining_time":2.148151104},
{"learn":[0.1369195321],"iteration":825,"passed_time":10.13761105,"remaining_time":2.135525814},
{"learn":[0.1368973634],"iteration":826,"passed_time":10.14850204,"remaining_time":2.122963547},
{"learn":[0.1368863038],"iteration":827,"passed_time":10.15900598,"remaining_time":2.110324914},
{"learn":[0.1368548033],"iteration":828,"passed_time":10.17038917,"remaining_time":2.097872797},
{"learn":[0.1368277916],"iteration":829,"passed_time":10.18159998,"remaining_time":2.085387948},
{"learn":[0.1368013951],"iteration":830,"passed_time":10.1964019,"remaining_time":2.073636488},
{"learn":[0.1367792459],"iteration":831,"passed_time":10.21378986,"remaining_time":2.062399875},
{"learn":[0.1367084583],"iteration":832,"passed_time":10.22597914,"remaining_time":2.050106263},
{"learn":[0.13667959],"iteration":833,"passed_time":10.23718554,"remaining_time":2.037617266},
{"learn":[0.1366670258],"iteration":834,"passed_time":10.2491809,"remaining_time":2.025287243},
{"learn":[0.136637503],"iteration":835,"passed_time":10.26188435,"remaining_time":2.013096931},
{"learn":[0.1366074101],"iteration":836,"passed_time":10.27306119,"remaining_time":2.000608092},
{"learn":[0.1365715131],"iteration":837,"passed_time":10.28421718,"remaining_time":1.988118357},
{"learn":[0.1365327936],"iteration":838,"passed_time":10.29532255,"remaining_time":1.975622086},
{"learn":[0.1365006239],"iteration":839,"passed_time":10.3090743,"remaining_time":1.963633199},
{"learn":[0.1364639342],"iteration":840,"passed_time":10.3239381,"remaining_time":1.951850366},
{"learn":[0.1364274117],"iteration":841,"passed_time":10.33627455,"remaining_time":1.939585961},
{"learn":[0.1363923409],"iteration":842,"passed_time":10.34886211,"remaining_time":1.927368151},
{"learn":[0.1363740121],"iteration":843,"passed_time":10.35994441,"remaining_time":1.914871242},
{"learn":[0.1363338684],"iteration":844,"passed_time":10.37139082,"remaining_time":1.90244447},
{"learn":[0.1363096807],"iteration":845,"passed_time":10.38239895,"remaining_time":1.889940235},
{"learn":[0.136271487],"iteration":846,"passed_time":10.39448893,"remaining_time":1.877634955},
{"learn":[0.1362493123],"iteration":847,"passed_time":10.40711953,"remaining_time":1.865427085},
{"learn":[0.1362068628],"iteration":848,"passed_time":10.41964543,"remaining_time":1.8531996},
{"learn":[0.1361754851],"iteration":849,"passed_time":10.43092999,"remaining_time":1.840752351},
{"learn":[0.1361524013],"iteration":850,"passed_time":10.44224487,"remaining_time":1.828313145},
{"learn":[0.1361278654],"iteration":851,"passed_time":10.45347721,"remaining_time":1.815862238},
{"learn":[0.1360934499],"iteration":852,"passed_time":10.46543732,"remaining_time":1.803539609},
{"learn":[0.1360714116],"iteration":853,"passed_time":10.47715449,"remaining_time":1.791176295},
{"learn":[0.1360601286],"iteration":854,"passed_time":10.48786507,"remaining_time":1.778643784},
{"learn":[0.1360392424],"iteration":855,"passed_time":10.50074449,"remaining_time":1.766480381},
{"learn":[0.1360289155],"iteration":856,"passed_time":10.51430291,"remaining_time":1.754428608},
{"learn":[0.1359955049],"iteration":857,"passed_time":10.52633688,"remaining_time":1.742121023},
{"learn":[0.1359745733],"iteration":858,"passed_time":10.53762936,"remaining_time":1.729692363},
{"learn":[0.1359336872],"iteration":859,"passed_time":10.55282341,"remaining_time":1.717901485},
{"learn":[0.1358916375],"iteration":860,"passed_time":10.56391399,"remaining_time":1.705440237},
{"learn":[0.1358520473],"iteration":861,"passed_time":10.58002639,"remaining_time":1.693786128},
{"learn":[0.135842309],"iteration":862,"passed_time":10.59608524,"remaining_time":1.682113184},
{"learn":[0.135826117],"iteration":863,"passed_time":10.61283159,"remaining_time":1.670538306},
{"learn":[0.1357851183],"iteration":864,"passed_time":10.62421142,"remaining_time":1.65811392},
{"learn":[0.1357435062],"iteration":865,"passed_time":10.63622199,"remaining_time":1.645789546},
{"learn":[0.1357055598],"iteration":866,"passed_time":10.64755857,"remaining_time":1.633362503},
{"learn":[0.1356787694],"iteration":867,"passed_time":10.65862741,"remaining_time":1.620897256},
{"learn":[0.1356376358],"iteration":868,"passed_time":10.66996648,"remaining_time":1.60847596},
{"learn":[0.1356169678],"iteration":869,"passed_time":10.68066578,"remaining_time":1.595961554},
{"learn":[0.1356023697],"iteration":870,"passed_time":10.69614903,"remaining_time":1.584159846},
{"learn":[0.1355712045],"iteration":871,"passed_time":10.71456069,"remaining_time":1.572779551},
{"learn":[0.1355499262],"iteration":872,"passed_time":10.72772253,"remaining_time":1.560619429},
{"learn":[0.1355123083],"iteration":873,"passed_time":10.74147533,"remaining_time":1.54854221},
{"learn":[0.1354770972],"iteration":874,"passed_time":10.75773204,"remaining_time":1.536818863},
{"learn":[0.1354466086],"iteration":875,"passed_time":10.77556215,"remaining_time":1.525307884},
{"learn":[0.1354312272],"iteration":876,"passed_time":10.78801092,"remaining_time":1.513027758},
{"learn":[0.1354033839],"iteration":877,"passed_time":10.8039802,"remaining_time":1.501236429},
{"learn":[0.1353475519],"iteration":878,"passed_time":10.8167152,"remaining_time":1.488990374},
{"learn":[0.1353254278],"iteration":879,"passed_time":10.82776327,"remaining_time":1.476513173},
{"learn":[0.1353034849],"iteration":880,"passed_time":10.83896869,"remaining_time":1.46406047},
{"learn":[0.1352590441],"iteration":881,"passed_time":10.85058553,"remaining_time":1.451665638},
{"learn":[0.135233973],"iteration":882,"passed_time":10.86226363,"remaining_time":1.439280685},
{"learn":[0.1351983369],"iteration":883,"passed_time":10.87302819,"remaining_time":1.426777455},
{"learn":[0.1351787067],"iteration":884,"passed_time":10.88445146,"remaining_time":1.414363749},
{"learn":[0.1351646685],"iteration":885,"passed_time":10.89575598,"remaining_time":1.401937},
{"learn":[0.1351354992],"iteration":886,"passed_time":10.9097896,"remaining_time":1.389860456},
{"learn":[0.1350994327],"iteration":887,"passed_time":10.92261439,"remaining_time":1.37762704},
{"learn":[0.1350642341],"iteration":888,"passed_time":10.9346629,"remaining_time":1.365295367},
{"learn":[0.1350381831],"iteration":889,"passed_time":10.94643417,"remaining_time":1.352930066},
{"learn":[0.1350032185],"iteration":890,"passed_time":10.95829995,"remaining_time":1.340577659},
{"learn":[0.1349913157],"iteration":891,"passed_time":10.96941521,"remaining_time":1.328135474},
{"learn":[0.1349627239],"iteration":892,"passed_time":10.98027189,"remaining_time":1.315665277},
{"learn":[0.1349339116],"iteration":893,"passed_time":10.990749,"remaining_time":1.303153685},
{"learn":[0.1349156189],"iteration":894,"passed_time":11.00530787,"remaining_time":1.291125504},
{"learn":[0.1348805856],"iteration":895,"passed_time":11.01759692,"remaining_time":1.278828214},
{"learn":[0.1348582493],"iteration":896,"passed_time":11.02963947,"remaining_time":1.266502637},
{"learn":[0.1348307067],"iteration":897,"passed_time":11.04062835,"remaining_time":1.254058009},
{"learn":[0.134790546],"iteration":898,"passed_time":11.05189128,"remaining_time":1.241647408},
{"learn":[0.1347610117],"iteration":899,"passed_time":11.06312033,"remaining_time":1.229235592},
{"learn":[0.1347189672],"iteration":900,"passed_time":11.07420193,"remaining_time":1.216810201},
{"learn":[0.134681469],"iteration":901,"passed_time":11.08562591,"remaining_time":1.204424988},
{"learn":[0.1346458947],"iteration":902,"passed_time":11.09661223,"remaining_time":1.19199489},
{"learn":[0.1346240254],"iteration":903,"passed_time":11.10932041,"remaining_time":1.17975084},
{"learn":[0.1345866158],"iteration":904,"passed_time":11.12112908,"remaining_time":1.16741134},
{"learn":[0.1345734017],"iteration":905,"passed_time":11.13289464,"remaining_time":1.155068538},
{"learn":[0.1345402449],"iteration":906,"passed_time":11.14389223,"remaining_time":1.142648266},
{"learn":[0.1345150446],"iteration":907,"passed_time":11.15468332,"remaining_time":1.130210204},
{"learn":[0.1344852709],"iteration":908,"passed_time":11.16750815,"remaining_time":1.117979363},
{"learn":[0.1344453549],"iteration":909,"passed_time":11.18649785,"remaining_time":1.10635693},
{"learn":[0.1344285943],"iteration":910,"passed_time":11.20129678,"remaining_time":1.094308906},
{"learn":[0.1343820413],"iteration":911,"passed_time":11.21800695,"remaining_time":1.082439267},
{"learn":[0.1343583046],"iteration":912,"passed_time":11.2347553,"remaining_time":1.070562662},
{"learn":[0.134316577],"iteration":913,"passed_time":11.25000464,"remaining_time":1.058534354},
{"learn":[0.1342899821],"iteration":914,"passed_time":11.26188545,"remaining_time":1.04618608},
{"learn":[0.134274184],"iteration":915,"passed_time":11.27330256,"remaining_time":1.033796304},
{"learn":[0.1342359891],"iteration":916,"passed_time":11.28927744,"remaining_time":1.021821186},
{"learn":[0.1342102657],"iteration":917,"passed_time":11.30761274,"remaining_time":1.010048196},
{"learn":[0.1341973854],"iteration":918,"passed_time":11.322481,"remaining_time":0.9979553438},
{"learn":[0.1341877466],"iteration":919,"passed_time":11.33391757,"remaining_time":0.9855580497},
{"learn":[0.1341614123],"iteration":920,"passed_time":11.34552679,"remaining_time":0.9731776512},
{"learn":[0.1341291394],"iteration":921,"passed_time":11.35794474,"remaining_time":0.9608673427},
{"learn":[0.1341014252],"iteration":922,"passed_time":11.36883323,"remaining_time":0.9484292079},
{"learn":[0.1340878562],"iteration":923,"passed_time":11.3796189,"remaining_time":0.9359859702},
{"learn":[0.1340426352],"iteration":924,"passed_time":11.3911491,"remaining_time":0.9236066835},
{"learn":[0.1340253649],"iteration":925,"passed_time":11.40294661,"remaining_time":0.9112505928},
{"learn":[0.133991749],"iteration":926,"passed_time":11.41680398,"remaining_time":0.8990579186},
{"learn":[0.1339752687],"iteration":927,"passed_time":11.42792624,"remaining_time":0.8866494498},
{"learn":[0.1339385572],"iteration":928,"passed_time":11.43968979,"remaining_time":0.8742927611},
{"learn":[0.1339081948],"iteration":929,"passed_time":11.45139626,"remaining_time":0.861933052},
{"learn":[0.1338903735],"iteration":930,"passed_time":11.46238028,"remaining_time":0.8495212021},
{"learn":[0.1338711006],"iteration":931,"passed_time":11.4739427,"remaining_time":0.8371546178},
{"learn":[0.1338449452],"iteration":932,"passed_time":11.48609079,"remaining_time":0.8248318147},
{"learn":[0.133811984],"iteration":933,"passed_time":11.49958706,"remaining_time":0.8126046529},
{"learn":[0.1337889153],"iteration":934,"passed_time":11.51435961,"remaining_time":0.8004635025},
{"learn":[0.1337690271],"iteration":935,"passed_time":11.52608349,"remaining_time":0.7881082727},
{"learn":[0.1337453519],"iteration":936,"passed_time":11.53780296,"remaining_time":0.7757540947},
{"learn":[0.1337256105],"iteration":937,"passed_time":11.54876999,"remaining_time":0.7633515344},
{"learn":[0.1337073804],"iteration":938,"passed_time":11.55945493,"remaining_time":0.7509337069},
{"learn":[0.1336745495],"iteration":939,"passed_time":11.57069665,"remaining_time":0.7385551055},
{"learn":[0.1336605229],"iteration":940,"passed_time":11.58139193,"remaining_time":0.726144659},
{"learn":[0.1336400092],"iteration":941,"passed_time":11.59388575,"remaining_time":0.713848592},
{"learn":[0.1336209034],"iteration":942,"passed_time":11.60689649,"remaining_time":0.7015833509},
{"learn":[0.1335899301],"iteration":943,"passed_time":11.62020264,"remaining_time":0.689334055},
{"learn":[0.133554957],"iteration":944,"passed_time":11.63212243,"remaining_time":0.6770018345},
{"learn":[0.1335203552],"iteration":945,"passed_time":11.6469841,"remaining_time":0.6648384159},
{"learn":[0.1334911566],"iteration":946,"passed_time":11.66327599,"remaining_time":0.6527493425},
{"learn":[0.1334567297],"iteration":947,"passed_time":11.68258318,"remaining_time":0.6408167992},
{"learn":[0.1334258319],"iteration":948,"passed_time":11.69418847,"remaining_time":0.6284548071},
{"learn":[0.1334072067],"iteration":949,"passed_time":11.70683522,"remaining_time":0.6161492222},
{"learn":[0.1333727182],"iteration":950,"passed_time":11.71927335,"remaining_time":0.6038321704},
{"learn":[0.1333423888],"iteration":951,"passed_time":11.73135836,"remaining_time":0.5914970603},
{"learn":[0.1333120388],"iteration":952,"passed_time":11.7442465,"remaining_time":0.5792020835},
{"learn":[0.1332881956],"iteration":953,"passed_time":11.75526522,"remaining_time":0.5668157234},
{"learn":[0.1332596759],"iteration":954,"passed_time":11.76609528,"remaining_time":0.5544233379},
{"learn":[0.1332228731],"iteration":955,"passed_time":11.78235426,"remaining_time":0.5422840872},
{"learn":[0.133188168],"iteration":956,"passed_time":11.79960703,"remaining_time":0.5301808803},
{"learn":[0.1331548896],"iteration":957,"passed_time":11.81965686,"remaining_time":0.5181895494},
{"learn":[0.1331436689],"iteration":958,"passed_time":11.8325984,"remaining_time":0.5058775125},
{"learn":[0.1331278211],"iteration":959,"passed_time":11.84435129,"remaining_time":0.4935146371},
{"learn":[0.1331070453],"iteration":960,"passed_time":11.85606492,"remaining_time":0.4811514378},
{"learn":[0.1330770165],"iteration":961,"passed_time":11.86750891,"remaining_time":0.4687789384},
{"learn":[0.1330677703],"iteration":962,"passed_time":11.87776118,"remaining_time":0.4563625793},
{"learn":[0.1330334931],"iteration":963,"passed_time":11.8906386,"remaining_time":0.4440487445},
{"learn":[0.1330087872],"iteration":964,"passed_time":11.90232215,"remaining_time":0.4316904408},
{"learn":[0.1329475764],"iteration":965,"passed_time":11.9149834,"remaining_time":0.4193679459},
{"learn":[0.1329124992],"iteration":966,"passed_time":11.92674101,"remaining_time":0.4070139124},
{"learn":[0.1328779112],"iteration":967,"passed_time":11.94034449,"remaining_time":0.394722132},
{"learn":[0.1328387761],"iteration":968,"passed_time":11.95200272,"remaining_time":0.382365412},
{"learn":[0.132816249],"iteration":969,"passed_time":11.96281632,"remaining_time":0.3699840098},
{"learn":[0.1327868483],"iteration":970,"passed_time":11.97477541,"remaining_time":0.3576400482},
{"learn":[0.1327343472],"iteration":971,"passed_time":11.98785346,"remaining_time":0.3453291119},
{"learn":[0.1327053185],"iteration":972,"passed_time":12.00048024,"remaining_time":0.3330040766},
{"learn":[0.1326794093],"iteration":973,"passed_time":12.01349035,"remaining_time":0.320688654},
{"learn":[0.1326567567],"iteration":974,"passed_time":12.02418281,"remaining_time":0.3083123798},
{"learn":[0.1326231525],"iteration":975,"passed_time":12.03661063,"remaining_time":0.2959822286},
{"learn":[0.1325966133],"iteration":976,"passed_time":12.04745489,"remaining_time":0.2836145982},
{"learn":[0.1325715552],"iteration":977,"passed_time":12.05871998,"remaining_time":0.2712595497},
{"learn":[0.1325659061],"iteration":978,"passed_time":12.06862461,"remaining_time":0.2588775453},
{"learn":[0.1325316637],"iteration":979,"passed_time":12.07958481,"remaining_time":0.246522139},
{"learn":[0.1325121447],"iteration":980,"passed_time":12.09077617,"remaining_time":0.2341740543},
{"learn":[0.1324845269],"iteration":981,"passed_time":12.10196653,"remaining_time":0.221828307},
{"learn":[0.1324579768],"iteration":982,"passed_time":12.11589363,"remaining_time":0.2095322398},
{"learn":[0.1324328251],"iteration":983,"passed_time":12.12697157,"remaining_time":0.1971865296},
{"learn":[0.1323762902],"iteration":984,"passed_time":12.14152136,"remaining_time":0.1848962644},
{"learn":[0.1323505262],"iteration":985,"passed_time":12.153824,"remaining_time":0.1725695091},
{"learn":[0.1323289706],"iteration":986,"passed_time":12.16634974,"remaining_time":0.1602457412},
{"learn":[0.1323064041],"iteration":987,"passed_time":12.17701668,"remaining_time":0.147898988},
{"learn":[0.132275797],"iteration":988,"passed_time":12.18896054,"remaining_time":0.1355698341},
{"learn":[0.1322489061],"iteration":989,"passed_time":12.20076889,"remaining_time":0.1232400898},
{"learn":[0.1322190455],"iteration":990,"passed_time":12.21468236,"remaining_time":0.1109305158},
{"learn":[0.1321956874],"iteration":991,"passed_time":12.22592591,"remaining_time":0.0985961767},
{"learn":[0.1321763338],"iteration":992,"passed_time":12.23923982,"remaining_time":0.08627862913},
{"learn":[0.132141648],"iteration":993,"passed_time":12.25043409,"remaining_time":0.07394628225},
{"learn":[0.1321094377],"iteration":994,"passed_time":12.26241693,"remaining_time":0.06162018556},
{"learn":[0.1320833393],"iteration":995,"passed_time":12.2738147,"remaining_time":0.0492924285},
{"learn":[0.1320494068],"iteration":996,"passed_time":12.28470385,"remaining_time":0.03696500656},
{"learn":[0.1320243464],"iteration":997,"passed_time":12.2958982,"remaining_time":0.02464107856},
{"learn":[0.1319850419],"iteration":998,"passed_time":12.31038696,"remaining_time":0.01232270967},
{"learn":[0.1319645197],"iteration":999,"passed_time":12.32545574,"remaining_time":0}
]}